Workbook
Name ACTUAR: PHVA!$B$70:$B$74
Name HACER: PHVA!$B$36:$B$65
Name PLANEAR: PHVA!$B$2:$B$35
Name VERIFICAR: PHVA!$B$66:$B$69

Sheet GRÁFICAS
A1: ACTIVO/INACTIVO | B1: (Todas)
A3: Etiquetas de fila | B3: Cuenta de Conexión | C3: Suma de PORCENTAJE
A4: AGROINSUMOS VILLACLARA SAS | B4: 1 | C4: 2
A5: ALMA BOTANICA SAS | B5: 8 | C5: 10
A6: ANA CAMPUZANO ARBOLEDA | B6: 10 | C6: 17.5
A7: BLACKRIVER FLOWERS SAS C I | B7: 13 | C7: 14.5
A8: BORJA FLOWERS SAS | B8: 10 | C8: 5
A9: CARNES MONTECARLO | B9: 5 | C9: 5 | K9: CONEXIONES SI -NO
A10: CI FLORES MUNDO COLORES SAS | B10: 12 | C10: 17.5 | K10: AVANCES DE CONEXIONES
A11: EMTURPE LIMITADA | B11: 12 | C11: 11
A12: ESTRUCTURAS METALICAS DEL CHOCO | B12: 1 | C12: 1
A13: FOTO SCANNER | B13: 3 | C13: 4
A14: HYDRANFLOWERS S.A.S | B14: 8 | C14: 5.5
A15: INVERSIONES VALLEJUELO S.A.S. | B15: 9 | C15: 11
A16: JORGE ELIECER GOMEZ | B16: 2 | C16: 0
A17: JULIAN GALLEGO CASTRO | B17: 8 | C17: 15
A18: LACTEOS BUENA VISTA SABORES NATURALES S A | B18: 10 | C18: 18
A19: LOPETRANS SAS | B19: 13 | C19: 23
A20: MADERAS SAN RAFAEL | B20: 11 | C20: 15
A21: OLGA LÓPEZ | B21: 6 | C21: 3.5
A22: PROSOLAR S.A.S | B22: 8 | C22: 8.5
... A29: Total general | B29: 205 | C29: 259.5
A31: Etiquetas de fila | B31: Cuenta de NIVEL DE RIESGO
A32: 1 | B32: 33
A33: 2 | B33: 51
A34: 3 | B34: 66
A35: 4 | B35: 30
A36: 5 | B36: 23
A37: (en blanco)
A38: Total general | B38: 203
A40: Etiquetas de fila | B40: Cuenta de NÚMERO DE EMPLEADOS
A41: AGROINSUMOS VILLACLARA SAS | B41: 1
A42: ALMA BOTANICA SAS | B42: 8
A43: ANA CAMPUZANO ARBOLEDA | B43: 10
A44: BLACKRIVER FLOWERS SAS C I | B44: 13
A45: BORJA FLOWERS SAS | B45: 10
A46: CARNES MONTECARLO | B46: 5
A47: CI FLORES MUNDO COLORES SAS | B47: 12
A48: EMTURPE LIMITADA | B48: 12
A49: ESTRUCTURAS METALICAS DEL CHOCO | B49: 1
A50: FOTO SCANNER | B50: 3
A51: HYDRANFLOWERS S.A.S | B51: 8
A52: INVERSIONES VALLEJUELO S.A.S. | B52: 9
... A66: Total general | B66: 195
A71: Nombre de la empresa | B71: DÍAS EN EL PROGRAMA
A72: CARNES MONTECARLO | B72: 90
A73: OLGA LÓPEZ | B73: 90
A74: TROPICAL1987 | B74: 90
A75: SUMINISTRO Y TRANSPORTE DE MATERIAL RIOS Y FLOREZ SAS | B75: 83
A76: TECCONS S.A.S | B76: 76
A77: SAÚL GÓMEZ | B77: 74
A78: MADERAS SAN RAFAEL | B78: 72
A79: LOPETRANS SAS | B79: 70
A80: INVERSIONES VALLEJUELO S.A.S. | B80: 66
A81: JULIAN GALLEGO CASTRO | B81: 66
A82: URANTUS GREENHOUSES S.A.S | B82: 65
A83: ANA CAMPUZANO ARBOLEDA | B83: 63
... A96: JORGE ELIECER GOMEZ | B96: 4
A100: Etiquetas de fila | B100: Suma de PORCENTAJE
A101: LOPETRANS SAS | B101: 23
A102: URANTUS GREENHOUSES S.A.S | B102: 18.5
A103: LACTEOS BUENA VISTA SABORES NATURALES S A | B103: 18
A104: ANA CAMPUZANO ARBOLEDA | B104: 17.5
A105: CI FLORES MUNDO COLORES SAS | B105: 17.5
A106: JULIAN GALLEGO CASTRO | B106: 15
A107: MADERAS SAN RAFAEL | B107: 15
A108: VANESSA VARGAS ALZATE | B108: 14
A109: SAÚL GÓMEZ | B109: 13
A110: TECCONS S.A.S | B110: 13
A111: EMTURPE LIMITADA | B111: 11
A112: INVERSIONES VALLEJUELO S.A.S. | B112: 11
... A124: JORGE ELIECER GOMEZ | B124: 0
A125: BORJA FLOWERS SAS
A129: Etiquetas de fila | B129: Suma de PORCENTAJE
A130: AGROINSUMOS VILLACLARA SAS | B130: 2
A131: ALMA BOTANICA SAS | B131: 10
A132: ANA CAMPUZANO ARBOLEDA | B132: 17.5
A133: BLACKRIVER FLOWERS SAS C I | B133: 14.5
A134: BORJA FLOWERS SAS | B134: 5
A135: CARNES MONTECARLO | B135: 5
A136: CI FLORES MUNDO COLORES SAS | B136: 17.5
A137: EMTURPE LIMITADA | B137: 11
A138: ESTRUCTURAS METALICAS DEL CHOCO | B138: 1
A139: FOTO SCANNER | B139: 4
A140: HYDRANFLOWERS S.A.S | B140: 5.5
A141: INVERSIONES VALLEJUELO S.A.S. | B141: 11
... A154: VANESSA VARGAS ALZATE | B154: 14
A155: (en blanco)
A156: Total general | B156: 259.5

Sheet CRM ANALISTAS
A1: FECHA INICIO DEL PROGRAMA | B1: MES DE INICIO COBERTURA | C1: MESES A CORTE 30 DE MAYO | D1: Día | E1: Programa | F1: Analista | G1: Nombre | H1: Tipo de documento | I1: N.Identificación | J1: Correo electrónico1 | K1: Número de celular | L1: Nombre de la empresa | M1: NIT | N1: Conexión | O1: Hora | P1: NIVEL DE RIESGO | Q1: VALOR | R1: ASISTENCIA | S1: CICLO | T1: ESTANDAR 0312 DE 2019 | U1: PORCENTAJE AVANCE | V1: Acompañamiento 1 | W1: FECHA DE INFORME | X1: DÍAS EN EL PROGRAMA | Y1: NÚMERO DE EMPLEADOS | Z1: ACTIVO/INACTIVO
A2: 45797 | B2: MAYO | C2: 1 | D2: MARTES | E2: TU EMPRESA SEGURA | F2: LUZ | G2: ALEXIS PÉREZ GÓMEZ | H2: Cédula de Ciudadanía | I2: 1040325965 | J2: contacto@villaclara.com.co | K2: 3132973915 | L2: AGROINSUMOS VILLACLARA SAS | M2: 901250630 | N2: 45797 | O2: 11:30 a.m | P2: 1 | Q2: =IF(OR(P2=1,P2=2,P2=3),106666,IF(OR(P2=4,P2=5),213000,"")) -> 106666 | R2: SI | S2: PLANEAR | T2: 1.0.6 Diagnóstico del Sistema de Gestión de Seguridad y Salud en el Trabajo (SG-SST) 0312 DE 2019 | U2: =IFERROR(VLOOKUP(T2,PHVA!$B$2:$C$74,2,0),0) -> 2 | V2: No firmo firma de termminos y condiciones por temas de no tener contraseña y usuario,se le presenta el programa .se le realiza evaluacion inicial | W2: 45807 | X2: =ABS(A2-W2) -> 10 | Y2: =VLOOKUP(M2,Hoja3!$L$2:$X$26,13,0) -> 14 | Z2: ACTIVO
A3: 45751 | B3: ABRIL | C3: 2 | D3: VIERNES | E3: TU EMPRESA SEGURA | F3: Juan Diego | G3: MERCEDES CARVAJAL OSPINA | H3: Cédula de Ciudadanía | I3: 21481666 | J3: mercedesemprendedora2023@gmail.com | K3: 3053436587 | L3: ALMA BOTANICA SAS | M3: 901817841 | N3: 45751 | O3: 11:30a.m | P3: 4 | Q3: =IF(OR(P3=1,P3=2,P3=3),106666,IF(OR(P3=4,P3=5),213000,"")) -> 213000 | R3: SI | S3: PLANEAR | T3: 1.0.4 Acompañamiiento/Asesoría sobre SGSST | U3: =IFERROR(VLOOKUP(T3,PHVA!$B$2:$C$74,2,0),0) -> 2 | V3: el dia martes 1 de abril se llamo a la empresa para poder validar si se peude contactar ya que s ehabia intentado anteriormente y no se habia logrado Presentación del Programa: Registro Usuario y contraseña, términos y condiciones y se explica reporte de incidentes y accidentes ante la ARL | W3: 45807 | X3: =ABS(A3-W3) -> 56 | Y3: =VLOOKUP(M3,Hoja3!$L$2:$X$26,13,0) -> 2 | Z3: ACTIVO
A4: 45758 | D4: VIERNES | E4: TU EMPRESA SEGURA | F4: Juan Diego | G4: MERCEDES CARVAJAL OSPINA | H4: Cédula de Ciudadanía | I4: 21481666 | J4: mercedesemprendedora2023@gmail.com | K4: 3053436587 | L4: ALMA BOTANICA SAS | M4: 901817841 | N4: 45758 | O4: 11:30a.m | P4: 4 | Q4: =IF(OR(P4=1,P4=2,P4=3),106666,IF(OR(P4=4,P4=5),213000,"")) -> 213000 | R4: SI | S4: PLANEAR | T4: 1.0.8 Ruta de Bienestar Savanna | U4: =IFERROR(VLOOKUP(T4,PHVA!$B$2:$C$74,2,0),0) -> 0 | V4: Se presenta el programa de Savanna con la Psicóloga Lorena, La primera conexión con la empresa se tuvo el día 11 de abril se hablo sobre toda la parte psicosocial que brinda la empresa -Savanna -asesorías psicológicas -Capacitaciones y talleres Se brindo toda la información de Savanna, se mostró plataforma y se envió el Excel para diligenciar información de los empleados y crear usuario y contraseña Se dio a conocer modalidad de asesorías psicológicas y la importancia de esta en las empresas Y al finalizar se dio a conocer las múltiples capacitaciones psicosociales que podemos trabajar durante el año. | W4: 45807 | X4: =ABS(A4-W4) -> 49 | Y4: =VLOOKUP(M4,Hoja3!$L$2:$X$26,13,0) -> 2 | Z4: ACTIVO
A5: 45765 | D5: VIERNES | E5: TU EMPRESA SEGURA | F5: Juan Diego | G5: MERCEDES CARVAJAL OSPINA | H5: Cédula de Ciudadanía | I5: 21481666 | J5: mercedesemprendedora2023@gmail.com | K5: 3053436587 | L5: ALMA BOTANICA SAS | M5: 901817841 | N5: 45765 | O5: 11:30a.m | P5: 4 | Q5: =IF(OR(P5=1,P5=2,P5=3),106666,IF(OR(P5=4,P5=5),213000,"")) -> 213000 | R5: NO CONEXIÓN | S5: PLANEAR | T5: 0.1 Trabajo autónomo analista en plataforma | U5: =IFERROR(VLOOKUP(T5,PHVA!$B$2:$C$74,2,0),0) -> 0.5 | V5: DIA FESTIVO | W5: 45807 | X5: =ABS(A5-W5) -> 42 | Y5: =VLOOKUP(M5,Hoja3!$L$2:$X$26,13,0) -> 2 | Z5: ACTIVO
A6: 45786 | D6: VIERNES | E6: TU EMPRESA SEGURA | F6: Juan Diego | G6: MERCEDES CARVAJAL OSPINA | H6: Cédula de Ciudadanía | I6: 21481666 | J6: mercedesemprendedora2023@gmail.com | K6: 3053436587 | L6: ALMA BOTANICA SAS | M6: 901817841 | N6: 45786 | O6: 11:30a.m | P6: 4 | Q6: =IF(OR(P6=1,P6=2,P6=3),106666,IF(OR(P6=4,P6=5),213000,"")) -> 213000 | R6: SI | S6: PLANEAR | T6: 1.1.1. Responsable del Sistema de Gestión de Seguridad y Salud en el Trabajo SG-SST | U6: =IFERROR(VLOOKUP(T6,PHVA!$B$2:$C$74,2,0),0) -> 0.5 | V6: se inicia con la asignacion de responsable del SGSST y se continua con el procedimiento de gestion documental; se deja pendiente la realizacion de los examenes medicos ocupacionales | W6: 45807 | X6: =ABS(A6-W6) -> 21 | Y6: =VLOOKUP(M6,Hoja3!$L$2:$X$26,13,0) -> 2 | Z6: ACTIVO
A7: 45793 | D7: VIERNES | E7: TU EMPRESA SEGURA | F7: Juan Diego | G7: MERCEDES CARVAJAL OSPINA | H7: Cédula de Ciudadanía | I7: 21481666 | J7: mercedesemprendedora2023@gmail.com | K7: 3053436587 | L7: ALMA BOTANICA SAS | M7: 901817841 | N7: 45793 | O7: 11:30a.m | P7: 4 | Q7: =IF(OR(P7=1,P7=2,P7=3),106666,IF(OR(P7=4,P7=5),213000,"")) -> 213000 | R7: SI | S7: PLANEAR | T7: 1.0.3 Navegando en la plataforma y beneficios del programa | U7: =IFERROR(VLOOKUP(T7,PHVA!$B$2:$C$74,2,0),0) -> 1 | V7: se realiza registro de empleados en plataforma | W7: 45807 | X7: =ABS(A7-W7) -> 14 | Y7: =VLOOKUP(M7,Hoja3!$L$2:$X$26,13,0) -> 2 | Z7: ACTIVO
A8: 45807 | D8: VIERNES | E8: TU EMPRESA SEGURA | F8: Juan Diego | G8: MERCEDES CARVAJAL OSPINA | H8: Cédula de Ciudadanía | I8: 21481666 | J8: mercedesemprendedora2023@gmail.com | K8: 3053436587 | L8: ALMA BOTANICA SAS | M8: 901817841 | N8: 45807 | O8: 11:30a.m | P8: 4 | Q8: =IF(OR(P8=1,P8=2,P8=3),106666,IF(OR(P8=4,P8=5),213000,"")) -> 213000 | R8: SI | S8: PLANEAR | T8: 1.0.4 Acompañamiiento/Asesoría sobre SGSST | U8: =IFERROR(VLOOKUP(T8,PHVA!$B$2:$C$74,2,0),0) -> 2 | V8: se consulta sobre estado de examenes médicos, se explican los tipos segun la normativa y se asignan responsabilidades | W8: 45807 | X8: =ABS(A8-W8) -> 0 | Y8: =VLOOKUP(M8,Hoja3!$L$2:$X$26,13,0) -> 2 | Z8: ACTIVO
A9: 45814 | D9: VIERNES | E9: TU EMPRESA SEGURA | F9: Juan Diego | G9: MERCEDES CARVAJAL OSPINA | H9: Cédula de Ciudadanía | I9: 21481666 | J9: mercedesemprendedora2023@gmail.com | K9: 3053436587 | L9: ALMA BOTANICA SAS | M9: 901817841 | N9: 45814 | O9: 11:30a.m | P9: 4 | Q9: =IF(OR(P9=1,P9=2,P9=3),106666,IF(OR(P9=4,P9=5),213000,"")) -> 213000 | R9: SI | S9: PLANEAR | T9: 1.0.4 Acompañamiiento/Asesoría sobre SGSST | U9: =IFERROR(VLOOKUP(T9,PHVA!$B$2:$C$74,2,0),0) -> 2 | V9: Se realiza, acta de actividades de alto riesgo, se ingresan planillas de examenes medicos | W9: 45807 | X9: =ABS(A9-W9) -> 7 | Y9: =VLOOKUP(M9,Hoja3!$L$2:$X$26,13,0) -> 2 | Z9: ACTIVO
A10: 45793 | D10: VIERNES | E10: TU EMPRESA SEGURA | F10: Juan Diego | G10: MERCEDES CARVAJAL OSPINA | H10: Cédula de Ciudadanía | I10: 21481666 | J10: mercedesemprendedora2023@gmail.com | K10: 3053436587 | L10: ALMA BOTANICA SAS | M10: 901817841 | N10: 45793 | P10: 4 | Q10: =IF(OR(P10=1,P10=2,P10=3),106666,IF(OR(P10=4,P10=5),213000,"")) -> 213000 | R10: SI | S10: PLANEAR | T10: 1.0.4 Acompañamiiento/Asesoría sobre SGSST | U10: =IFERROR(VLOOKUP(T10,PHVA!$B$2:$C$74,2,0),0) -> 2 | V10: Se xplica la importancia de los examenes médicos, como hacer lagestion, y se empieza a registrar el personal | W10: 45807 | X10: =ABS(A10-W10) -> 14 | Y10: =VLOOKUP(M10,Hoja3!$L$2:$X$26,13,0) -> 2 | Z10: ACTIVO
A11: 45744 | B11: MARZO | C11: 3 | D11: VIERNES | E11: TU EMPRESA SEGURA | F11: Cristhian | G11: Ana Maria Campuzano Arboleda | H11: Cédula de Ciudadanía | I11: 1007445947 | J11: anam_campuzano@hotmail.com | K11: 3217213077 | L11: ANA CAMPUZANO ARBOLEDA | M11: 1007445947 | N11: 45744 | O11: 11:30a.m | P11: 2 | Q11: =IF(OR(P11=1,P11=2,P11=3),106666,IF(OR(P11=4,P11=5),213000,"")) -> 106666 | R11: SI | S11: PLANEAR | T11: 1.0.0 Bienvenida | U11: =IFERROR(VLOOKUP(T11,PHVA!$B$2:$C$74,2,0),0) -> 1 | V11: Bienvenida al programa, se le explica detalladamente en que consiste y la duración estimada, se Indica cómo firmar los términos y condiciones, se agenda la reunión periódica, semanal, los viernes de 11:30 a 12:15pm | W11: 45807 | X11: =ABS(A11-W11) -> 63 | Y11: =VLOOKUP(M11,Hoja3!$L$2:$X$26,13,0) -> 2 | Z11: ACTIVO
A12: 45751 | D12: VIERNES | E12: TU EMPRESA SEGURA | F12: Cristhian | G12: Ana Maria Campuzano Arboleda | H12: Cédula de Ciudadanía | I12: 1007445947 | J12: anam_campuzano@hotmail.com | K12: 3217213077 | L12: ANA CAMPUZANO ARBOLEDA | M12: 1007445947 | N12: 45751 | O12: 11:30a.m | P12: 2 | Q12: =IF(OR(P12=1,P12=2,P12=3),106666,IF(OR(P12=4,P12=5),213000,"")) -> 106666 | R12: SI | S12: PLANEAR | T12: 1.0.5 Diagnóstico de Madurez | U12: =IFERROR(VLOOKUP(T12,PHVA!$B$2:$C$74,2,0),0) -> 3 | V12: Se realiza el diagnostico de madurez | W12: 45807 | Y12: =VLOOKUP(M12,Hoja3!$L$2:$X$26,13,0) -> 2 | Z12: ACTIVO
A13: 45758 | D13: VIERNES | E13: TU EMPRESA SEGURA | F13: Cristhian | G13: Ana Maria Campuzano Arboleda | H13: Cédula de Ciudadanía | I13: 1007445947 | J13: anam_campuzano@hotmail.com | K13: 3217213077 | L13: ANA CAMPUZANO ARBOLEDA | M13: 1007445947 | N13: 45758 | O13: 11:30a.m | P13: 2 | Q13: =IF(OR(P13=1,P13=2,P13=3),106666,IF(OR(P13=4,P13=5),213000,"")) -> 106666 | R13: SI | S13: PLANEAR | T13: 1.0.6 Diagnóstico del Sistema de Gestión de Seguridad y Salud en el Trabajo (SG-SST) 0312 DE 2019 | U13: =IFERROR(VLOOKUP(T13,PHVA!$B$2:$C$74,2,0),0) -> 2 | V13: Se realiza la evaluacion inicial del sistema de gestion, se dan recomendaciones iniciales | W13: 45807 | X13: =ABS(A13-W13) -> 49 | Y13: =VLOOKUP(M13,Hoja3!$L$2:$X$26,13,0) -> 2 | Z13: ACTIVO
A14: 45765 | D14: VIERNES | E14: TU EMPRESA SEGURA | F14: LUZ | G14: Ana Maria Campuzano Arboleda | H14: Cédula de Ciudadanía | I14: 1007445947 | J14: anam_campuzano@hotmail.com | K14: 3217213077 | L14: ANA CAMPUZANO ARBOLEDA | M14: 1007445947 | N14: 45765 | O14: 11:30a.m | P14: 2 | Q14: =IF(OR(P14=1,P14=2,P14=3),106666,IF(OR(P14=4,P14=5),213000,"")) -> 106666 | R14: NO | S14: PLANEAR | T14: 1.0.4 Acompañamiiento/Asesoría sobre SGSST | U14: =IFERROR(VLOOKUP(T14,PHVA!$B$2:$C$74,2,0),0) -> 2 | V14: El 24 de abril del 2025 me transfieren a Doña ana ,Era del analista Cristian. | W14: 45807 | X14: =ABS(A14-W14) -> 42 | Y14: =VLOOKUP(M14,Hoja3!$L$2:$X$26,13,0) -> 2 | Z14: ACTIVO
A15: 45771 | D15: JUEVES | E15: TU EMPRESA SEGURA | F15: LUZ | G15: Ana Maria Campuzano Arboleda | H15: Cédula de Ciudadanía | I15: 1007445947 | J15: anam_campuzano@hotmail.com | K15: 3217213077 | L15: ANA CAMPUZANO ARBOLEDA | M15: 1007445947 | N15: 45772 | O15: 11:30a.m | P15: 2 | Q15: =IF(OR(P15=1,P15=2,P15=3),106666,IF(OR(P15=4,P15=5),213000,"")) -> 106666 | R15: SI | S15: PLANEAR | T15: 1.0.1 Firma de Términos y Condiciones | U15: =IFERROR(VLOOKUP(T15,PHVA!$B$2:$C$74,2,0),0) -> 1 | V15: La señora ana refiere que con en analista Cristian se realizo,Firma de documento de terminos y condiciones,cuenta con contraseña y usuario,se le realizo el diagnostico inicial.Hoy 24 de abril,se le informanuevamente del programa,se actualiza informacion de empresa,se le solicita documentos rut ,camara y comercio etc,se le informa del procedimiento del archivo documental y su importancia para continuar diligenciando documentos y se le explica el numerar 1.1.4. | W15: 45807 | X15: =ABS(A15-W15) -> 36 | Y15: =VLOOKUP(M15,Hoja3!$L$2:$X$26,13,0) -> 2 | Z15: ACTIVO
A16: 45724 | D16: JUEVES | E16: TU EMPRESA SEGURA | F16: LUZ | G16: Ana Maria Campuzano Arboleda | H16: Cédula de Ciudadanía | I16: 1007445947 | J16: anam_campuzano@hotmail.com | K16: 3217213077 | L16: ANA CAMPUZANO ARBOLEDA | M16: 1007445947 | N16: 45785 | O16: 11:30a.m | P16: 2 | Q16: =IF(OR(P16=1,P16=2,P16=3),106666,IF(OR(P16=4,P16=5),213000,"")) -> 106666 | R16: SI | S16: PLANEAR | T16: 1.1.1. Responsable del Sistema de Gestión de Seguridad y Salud en el Trabajo SG-SST | U16: =IFERROR(VLOOKUP(T16,PHVA!$B$2:$C$74,2,0),0) -> 0.5 | V16: se realiza archivo documental,se revisa numeral 1.1.4,tarea subir el perfilsociodemogradico,se realiza diligenciamiento del responsable sst. | W16: 45807 | X16: =ABS(A16-W16) -> 83 | Y16: =VLOOKUP(M16,Hoja3!$L$2:$X$26,13,0) -> 2 | Z16: ACTIVO
A17: 45731 | D17: JUEVES | E17: TU EMPRESA SEGURA | F17: LUZ | G17: Ana Maria Campuzano Arboleda | H17: Cédula de Ciudadanía | I17: 1007445947 | J17: anam_campuzano@hotmail.com | K17: 3217213077 | L17: ANA CAMPUZANO ARBOLEDA | M17: 1007445947 | N17: 45792 | O17: 11:30a.m | P17: 2 | Q17: =IF(OR(P17=1,P17=2,P17=3),106666,IF(OR(P17=4,P17=5),213000,"")) -> 106666 | R17: NO | S17: PLANEAR | T17: 1.0.4 Acompañamiiento/Asesoría sobre SGSST | U17: =IFERROR(VLOOKUP(T17,PHVA!$B$2:$C$74,2,0),0) -> 2 | V17: Envia correo de inconveniente en conexion,se deja tareas por correo para proximo encuentro. | W17: 45807 | X17: =ABS(A17-W17) -> 76 | Y17: =VLOOKUP(M17,Hoja3!$L$2:$X$26,13,0) -> 2 | Z17: ACTIVO
A18: 45738 | D18: JUEVES | E18: TU EMPRESA SEGURA | F18: LUZ | G18: Ana Maria Campuzano Arboleda | H18: Cédula de Ciudadanía | I18: 1007445947 | J18: anam_campuzano@hotmail.com | K18: 3217213077 | L18: ANA CAMPUZANO ARBOLEDA | M18: 1007445947 | N18: 45799 | O18: 10:35a.m | P18: 2 | Q18: =IF(OR(P18=1,P18=2,P18=3),106666,IF(OR(P18=4,P18=5),213000,"")) -> 106666 | R18: SI | S18: PLANEAR | T18: 1.0.4 Acompañamiiento/Asesoría sobre SGSST | U18: =IFERROR(VLOOKUP(T18,PHVA!$B$2:$C$74,2,0),0) -> 2 | V18: Se verifica numerales del planear en archivo documental,se explica el tema de archivo documental del hacer y para la proxima reunion se realizara el tema de plan anual de trabajo. | W18: 45807 | X18: =ABS(A18-W18) -> 69 | Y18: =VLOOKUP(M18,Hoja3!$L$2:$X$26,13,0) -> 2 | Z18: ACTIVO
A19: 45745 | D19: JUEVES | E19: TU EMPRESA SEGURA | F19: LUZ | G19: Ana Maria Campuzano Arboleda | H19: Cédula de Ciudadanía | I19: 1007445947 | J19: anam_campuzano@hotmail.com | K19: 3217213077 | L19: ANA CAMPUZANO ARBOLEDA | M19: 1007445947 | N19: 45806 | O19: 10:35a.m | P19: 2 | Q19: =IF(OR(P19=1,P19=2,P19=3),106666,IF(OR(P19=4,P19=5),213000,"")) -> 106666 | R19: NO | S19: PLANEAR | T19: 1.0.4 Acompañamiiento/Asesoría sobre SGSST | U19: =IFERROR(VLOOKUP(T19,PHVA!$B$2:$C$74,2,0),0) -> 2 | V19: Envia correo de inconveniente en conexion,por temas de cita medica que se cruzaba con la conexion.solicita reprogramar para otro dia o enviarle tareaspor correo. | W19: 45807 | X19: =ABS(A19-W19) -> 62 | Y19: =VLOOKUP(M19,Hoja3!$L$2:$X$26,13,0) -> 2 | Z19: ACTIVO
A20: 45813 | D20: JUEVES | E20: TU EMPRESA SEGURA | F20: LUZ | G20: Ana Maria Campuzano Arboleda | H20: Cédula de Ciudadanía | I20: 1007445947 | J20: anam_campuzano@hotmail.com | K20: 3217213077 | L20: ANA CAMPUZANO ARBOLEDA | M20: 1007445947 | N20: 45813 | O20: 10:35a.m | P20: 2 | Q20: =IF(OR(P20=1,P20=2,P20=3),106666,IF(OR(P20=4,P20=5),213000,"")) -> 106666 | R20: SI | S20: PLANEAR | T20: 2.5.1 Archivo o retención documental del Sistema de Gestión en Seguridad y Salud en el Trabajo SG-SST | U20: =IFERROR(VLOOKUP(T20,PHVA!$B$2:$C$74,2,0),0) -> 2 | V20: LA señora ana refiere que esta interesada en continuar con lña plataforma,solo que tiene un nuevo trabajo y no le dara tiempo para conectarse,enviara correo para reprogramar tiempos o espacio de conexion ,por este motivo solo se realiza numeral 2.5.1 ,se verifica 1.1.4 ,se realiza verificacion del 3.1.1.1.,depende de la solucion al correo que envie doña ana se realizara cronograma teniendo encuenta que es solo ella y un trabajador. | W20: 45807 | X20: =ABS(A20-W20) -> 6 | Y20: =VLOOKUP(M20,Hoja3!$L$2:$X$26,13,0) -> 2 | Z20: ACTIVO
A21: 45751 | B21: ABRIL | C21: 2 | D21: VIERNES | E21: TU EMPRESA SEGURA | F21: Juan Diego | G21: MELISSA MARIA ROMAN BURITICA | H21: Cédula de Ciudadanía | I21: 1040039119 | J21: gestionhumana@blackriverflowers.com | K21: 3173882936 | L21: BLACKRIVER FLOWERS SAS C I | M21: 900841005 | N21: 45751 | O21: 10:40a. m. | P21: 3 | Q21: =IF(OR(P21=1,P21=2,P21=3),106666,IF(OR(P21=4,P21=5),213000,"")) -> 106666 | R21: SI | S21: PLANEAR | T21: 1.0.1 Firma de Términos y Condiciones | U21: =IFERROR(VLOOKUP(T21,PHVA!$B$2:$C$74,2,0),0) -> 1 | V21: el dia viernes 21 de marzo se llamo a la empresa para validar la llegada del correo electronico con el usuario y la contraseña a lo cual indicaron que si les llego y que no han tenido ningun inconveniente | W21: 45807 | X21: =ABS(A21-W21) -> 56 | Y21: =VLOOKUP(M21,Hoja3!$L$2:$X$26,13,0) -> 55 | Z21: ACTIVO
A22: 45758 | D22: VIERNES | E22: TU EMPRESA SEGURA | F22: Juan Diego | G22: MELISSA MARIA ROMAN BURITICA | H22: Cédula de Ciudadanía | I22: 1040039119 | J22: gestionhumana@blackriverflowers.com | K22: 3173882936 | L22: BLACKRIVER FLOWERS SAS C I | M22: 900841005 | N22: 45758 | O22: 10:40a. m. | P22: 3 | Q22: =IF(OR(P22=1,P22=2,P22=3),106666,IF(OR(P22=4,P22=5),213000,"")) -> 106666 | R22: NO | S22: PLANEAR | T22: 0. No participación de empresa | V22: Se actualiza plantilla de evaluacion inicial para la empresa, y seempieza con la codificacion , y procedimiento de listado maestro de documentos | W22: 45807 | X22: =ABS(A22-W22) -> 49 | Y22: =VLOOKUP(M22,Hoja3!$L$2:$X$26,13,0) -> 55 | Z22: ACTIVO
A23: 45765 | D23: VIERNES | E23: TU EMPRESA SEGURA | F23: Juan Diego | G23: MELISSA MARIA ROMAN BURITICA | H23: Cédula de Ciudadanía | I23: 1040039119 | J23: gestionhumana@blackriverflowers.com | K23: 3173882936 | L23: BLACKRIVER FLOWERS SAS C I | M23: 900841005 | N23: 45765 | O23: 10:40a. m. | P23: 3 | Q23: =IF(OR(P23=1,P23=2,P23=3),106666,IF(OR(P23=4,P23=5),213000,"")) -> 106666 | R23: NO | S23: PLANEAR | T23: 0. No participación de empresa | U23: =IFERROR(VLOOKUP(T23,PHVA!$B$2:$C$74,2,0),0) -> 0 | V23: se continua con la codificacion de documentos | W23: 45807 | X23: =ABS(A23-W23) -> 42 | Y23: =VLOOKUP(M23,Hoja3!$L$2:$X$26,13,0) -> 55 | Z23: ACTIVO
A24: 45779 | D24: VIERNES | E24: TU EMPRESA SEGURA | F24: Juan Diego | G24: MELISSA MARIA ROMAN BURITICA | H24: Cédula de Ciudadanía | I24: 1040039119 | J24: gestionhumana@blackriverflowers.com | K24: 3173882936 | L24: BLACKRIVER FLOWERS SAS C I | M24: 900841005 | N24: 45779 | O24: 10:40a. m. | P24: 3 | Q24: =IF(OR(P24=1,P24=2,P24=3),106666,IF(OR(P24=4,P24=5),213000,"")) -> 106666 | R24: NO | S24: PLANEAR | T24: 0. No participación de empresa | U24: =IFERROR(VLOOKUP(T24,PHVA!$B$2:$C$74,2,0),0) -> 0 | V24: no se conecta, se realizan las llamadas por wassap y telefonicas, y no se recibe respuesta, se gestiona documento de asignaion de responsable | W24: 45807 | X24: =ABS(A24-W24) -> 28 | Y24: =VLOOKUP(M24,Hoja3!$L$2:$X$26,13,0) -> 55 | Z24: ACTIVO
A25: 45786 | D25: VIERNES | E25: TU EMPRESA SEGURA | F25: Juan Diego | G25: MELISSA MARIA ROMAN BURITICA | H25: Cédula de Ciudadanía | I25: 1040039119 | J25: gestionhumana@blackriverflowers.com | K25: 3173882936 | L25: BLACKRIVER FLOWERS SAS C I | M25: 900841005 | N25: 45786 | O25: 10:40a. m. | P25: 3 | Q25: =IF(OR(P25=1,P25=2,P25=3),106666,IF(OR(P25=4,P25=5),213000,"")) -> 106666 | R25: NO | S25: PLANEAR | T25: 0. No participación de empresa | U25: =IFERROR(VLOOKUP(T25,PHVA!$B$2:$C$74,2,0),0) -> 0 | V25: no se conecta, escribo via whatsap, y me responden que no habia recibido la invitacion y por ende no estaba agendada para atenderme, verifico con la compañera Paula, y verificamos que la invitacion fue enviada al correo asignado por el cliente | W25: 45807 | X25: =ABS(A25-W25) -> 21 | Y25: =VLOOKUP(M25,Hoja3!$L$2:$X$26,13,0) -> 55 | Z25: ACTIVO
A26: 45793 | D26: VIERNES | E26: TU EMPRESA SEGURA | F26: LUZ | G26: MELISSA MARIA ROMAN BURITICA | H26: Cédula de Ciudadanía | I26: 1040039119 | J26: gestionhumana@blackriverflowers.com | K26: 3173882936 | L26: BLACKRIVER FLOWERS SAS C I | M26: 900841005 | N26: 45792 | O26: 8:05a. m. | P26: 3 | Q26: =IF(OR(P26=1,P26=2,P26=3),106666,IF(OR(P26=4,P26=5),213000,"")) -> 106666 | R26: SI | S26: PLANEAR | T26: 1.1.4 Afiliación al Sistema General de Riesgos Laborales | U26: =IFERROR(VLOOKUP(T26,PHVA!$B$2:$C$74,2,0),0) -> 0.5 | V26: Se realiza la conexion a las 8:41am no le fue posible conectarse antes,se le verifica firma de terminos y condiciones,la señora melissa actualizo documentos de la empresa en la plataforma,adicional de le indica como se realiza el numeral 1.1.4 y el 2.5.1 ,subira el perfil sociodemografico y se le endica que para realizar capacitaciones debemos realizar el diagnostico inicial el 22 de mayo y ahi ingresamos a realizar cronograma. | W26: 45807 | X26: =ABS(A26-W26) -> 14 | Y26: =VLOOKUP(M26,Hoja3!$L$2:$X$26,13,0) -> 55 | Z26: ACTIVO
A27: 45800 | D27: VIERNES | E27: TU EMPRESA SEGURA | F27: LUZ | G27: MELISSA MARIA ROMAN BURITICA | H27: Cédula de Ciudadanía | I27: 1040039119 | J27: gestionhumana@blackriverflowers.com | K27: 3173882936 | L27: BLACKRIVER FLOWERS SAS C I | M27: 900841005 | N27: 45799 | O27: 8:05a. m. | P27: 3 | Q27: =IF(OR(P27=1,P27=2,P27=3),106666,IF(OR(P27=4,P27=5),213000,"")) -> 106666 | R27: SI | S27: PLANEAR | T27: 1.0.6 Diagnóstico del Sistema de Gestión de Seguridad y Salud en el Trabajo (SG-SST) 0312 DE 2019 | U27: =IFERROR(VLOOKUP(T27,PHVA!$B$2:$C$74,2,0),0) -> 2 | V27: Se realiza la evaluacion inicial del diagnostico sst,se le solicita documentos para actualizacion de datos e empresa. | W27: 45807 | X27: =ABS(A27-W27) -> 7 | Y27: =VLOOKUP(M27,Hoja3!$L$2:$X$26,13,0) -> 55 | Z27: ACTIVO
A28: 45803 | D28: VIERNES | E28: TU EMPRESA SEGURA | F28: LUZ | G28: MELISSA MARIA ROMAN BURITICA | H28: Cédula de Ciudadanía | I28: 1040039119 | J28: gestionhumana@blackriverflowers.com | K28: 3173882936 | L28: BLACKRIVER FLOWERS SAS C I | M28: 900841005 | N28: 45803 | O28: 8:05a. m. | P28: 3 | Q28: =IF(OR(P28=1,P28=2,P28=3),106666,IF(OR(P28=4,P28=5),213000,"")) -> 106666 | R28: NO | S28: PLANEAR | T28: 1.0.9 Savanna Ruta de Bienestar | U28: =IFERROR(VLOOKUP(T28,PHVA!$B$2:$C$74,2,0),0) -> 4 | V28: Por temas de energia en sistegra, no fue posible la conexiony reprogramar tampoco por agenda copada. | W28: 45807 | X28: =ABS(A28-W28) -> 4 | Y28: =VLOOKUP(M28,Hoja3!$L$2:$X$26,13,0) -> 55 | Z28: ACTIVO
A29: 45807 | D29: VIERNES | E29: TU EMPRESA SEGURA | F29: LUZ | G29: MELISSA MARIA ROMAN BURITICA | H29: Cédula de Ciudadanía | I29: 1040039119 | J29: gestionhumana@blackriverflowers.com | K29: 3173882936 | L29: BLACKRIVER FLOWERS SAS C I | M29: 900841005 | N29: 45806 | O29: 8:05a. m. | P29: 3 | Q29: =IF(OR(P29=1,P29=2,P29=3),106666,IF(OR(P29=4,P29=5),213000,"")) -> 106666 | R29: NO | S29: PLANEAR | T29: 0. No participación de empresa | U29: =IFERROR(VLOOKUP(T29,PHVA!$B$2:$C$74,2,0),0) -> 0 | V29: Por temas de energia en sistegra, no fue posible la conexiony reprogramar tampoco por agenda copada. | W29: 45807 | X29: =ABS(A29-W29) -> 0 | Y29: =VLOOKUP(M29,Hoja3!$L$2:$X$26,13,0) -> 55 | Z29: ACTIVO
A30: 45814 | D30: VIERNES | E30: TU EMPRESA SEGURA | F30: LUZ | G30: MELISSA MARIA ROMAN BURITICA | H30: Cédula de Ciudadanía | I30: 1040039119 | J30: gestionhumana@blackriverflowers.com | K30: 3173882936 | L30: BLACKRIVER FLOWERS SAS C I | M30: 900841005 | N30: 45813 | O30: 8:05a. m. | P30: 3 | Q30: =IF(OR(P30=1,P30=2,P30=3),106666,IF(OR(P30=4,P30=5),213000,"")) -> 106666 | R30: SI | S30: PLANEAR | T30: 1.2.1 Programa Capacitación promoción y prevención PYP | U30: =IFERROR(VLOOKUP(T30,PHVA!$B$2:$C$74,2,0),0) -> 2 | V30: se visualisa terminos y condiciones firmada y compartida por correo,se le compartira cronograma de capacitaciones y cronograma anual de cumplimiento 0312,se verificara la contraseña y usuario para plataforma de capacitacion,no tiene datos para ingresar y solicita modificacion en representante legal porque no es ella ,melisa es de gestion humana. | W30: 45807 | X30: =ABS(A30-W30) -> 7 | Y30: =VLOOKUP(M30,Hoja3!$L$2:$X$26,13,0) -> 55 | Z30: ACTIVO
A31: 45786 | D31: VIERNES | E31: TU EMPRESA SEGURA | F31: LUZ | G31: MELISSA MARIA ROMAN BURITICA | H31: Cédula de Ciudadanía | I31: 1040039119 | J31: gestionhumana@blackriverflowers.com | K31: 3173882936 | L31: BLACKRIVER FLOWERS SAS C I | M31: 900841005 | N31: 45786 | O31: 10:40a. m. | P31: 3 | Q31: =IF(OR(P31=1,P31=2,P31=3),106666,IF(OR(P31=4,P31=5),213000,"")) -> 106666 | R31: SI | S31: PLANEAR | T31: 1.0.2 Socialización SGSST | U31: =IFERROR(VLOOKUP(T31,PHVA!$B$2:$C$74,2,0),0) -> 2 | V31: estando conectado a la hora en punto, dicen que no asistira, ya que el 12 de mayo se reuniran con Laura DIaz | W31: 45807 | X31: =ABS(A31-W31) -> 21 | Y31: =VLOOKUP(M31,Hoja3!$L$2:$X$26,13,0) -> 55 | Z31: ACTIVO
A32: 45789 | D32: LUNES | E32: TU EMPRESA SEGURA | F32: LUZ | G32: MELISSA MARIA ROMAN BURITICA | H32: Cédula de Ciudadanía | I32: 1040039119 | J32: gestionhumana@blackriverflowers.com | K32: 3173882936 | L32: BLACKRIVER FLOWERS SAS C I | M32: 900841005 | N32: 45789 | P32: 3 | Q32: =IF(OR(P32=1,P32=2,P32=3),106666,IF(OR(P32=4,P32=5),213000,"")) -> 106666 | R32: SI | S32: PLANEAR | T32: 1.0.3 Navegando en la plataforma y beneficios del programa | U32: =IFERROR(VLOOKUP(T32,PHVA!$B$2:$C$74,2,0),0) -> 1 | V32: Se muestran los beneficios del programa y se rrealiza cambio de analista con nuevo horario para facilitar al cliente las conexiones. | W32: 45789 | X32: =ABS(A32-W32) -> 0 | Y32: =VLOOKUP(M32,Hoja3!$L$2:$X$26,13,0) -> 55 | Z32: ACTIVO
A33: 45793 | D33: VIERNES | E33: TU EMPRESA SEGURA | F33: Juan Diego | G33: MELISSA MARIA ROMAN BURITICA | H33: Cédula de Ciudadanía | I33: 1040039119 | J33: gestionhumana@blackriverflowers.com | K33: 3173882936 | L33: BLACKRIVER FLOWERS SAS C I | M33: 900841005 | N33: 45786 | O33: 10:40a. m. | P33: 3 | Q33: =IF(OR(P33=1,P33=2,P33=3),106666,IF(OR(P33=4,P33=5),213000,"")) -> 106666 | R33: SI | S33: PLANEAR | T33: 1.0.2 Socialización SGSST | U33: =IFERROR(VLOOKUP(T33,PHVA!$B$2:$C$74,2,0),0) -> 2 | V33: menciona qe realiza cambio de horario autorizado por Laura Diaz | W33: 45807 | X33: =ABS(A33-W33) -> 14 | Y33: =VLOOKUP(M33,Hoja3!$L$2:$X$26,13,0) -> 55 | Z33: ACTIVO
A34: 45751 | B34: ABRIL | C34: 2 | D34: VIERNES | E34: TU EMPRESA SEGURA | F34: Juan Diego | G34: CLAUDIA PATRICIA MOLINA SANTOS | H34: Cédula de Ciudadanía | I34: 1070989191 | J34: clau300625@hotmail.es | K34: 3132973915 | L34: BORJA FLOWERS SAS | M34: 901546567 | N34: 45751 | O34: 3:55p. m. | P34: 3 | Q34: =IF(OR(P34=1,P34=2,P34=3),106666,IF(OR(P34=4,P34=5),213000,"")) -> 106666 | R34: SI | S34: PLANEAR | T34: 1.0.0 Bienvenida | U34: =IFERROR(VLOOKUP(T34,PHVA!$B$2:$C$74,2,0),0) -> 1 | V34: el dia viernes 21 de marzo se llamo a la empresa para validar la llegada del correo electronico con el usuario y la contraseña a lo cual indicaron que si les llego y que no han tenido ningun inconveniente | W34: 45807 | X34: =ABS(A34-W34) -> 56 | Y34: =VLOOKUP(M34,Hoja3!$L$2:$X$26,13,0) -> 30 | Z34: ACTIVO
A35: 45758 | D35: VIERNES | E35: TU EMPRESA SEGURA | F35: Juan Diego | G35: CLAUDIA PATRICIA MOLINA SANTOS | H35: Cédula de Ciudadanía | I35: 1070989191 | J35: clau300625@hotmail.es | K35: 3132973915 | L35: BORJA FLOWERS SAS | M35: 901546567 | N35: 45758 | O35: 3:55p. m. | P35: 3 | Q35: =IF(OR(P35=1,P35=2,P35=3),106666,IF(OR(P35=4,P35=5),213000,"")) -> 106666 | R35: SI | S35: PLANEAR | T35: 0. No participación de empresa | U35: =IFERROR(VLOOKUP(T35,PHVA!$B$2:$C$74,2,0),0) -> 0 | V35: Se reagenda espacio por calamidad de analista, se reprograma para el día 12 de abril | W35: 45807 | X35: =ABS(A35-W35) -> 49 | Y35: =VLOOKUP(M35,Hoja3!$L$2:$X$26,13,0) -> 30 | Z35: ACTIVO
A36: 45765 | D36: VIERNES | E36: TU EMPRESA SEGURA | F36: Juan Diego | G36: CLAUDIA PATRICIA MOLINA SANTOS | H36: Cédula de Ciudadanía | I36: 1070989191 | J36: clau300625@hotmail.es | K36: 3132973915 | L36: BORJA FLOWERS SAS | M36: 901546567 | N36: 45765 | O36: 3:55p. m. | P36: 3 | Q36: =IF(OR(P36=1,P36=2,P36=3),106666,IF(OR(P36=4,P36=5),213000,"")) -> 106666 | R36: CONEXIÓN AUTÓNOMA DE ANALISTA | S36: PLANEAR | T36: 0.1 Trabajo autónomo analista en plataforma | U36: =IFERROR(VLOOKUP(T36,PHVA!$B$2:$C$74,2,0),0) -> 0.5 | V36: Se adelanta documento de asignacion del responsable | W36: 45807 | X36: =ABS(A36-W36) -> 42 | Y36: =VLOOKUP(M36,Hoja3!$L$2:$X$26,13,0) -> 30 | Z36: ACTIVO
A37: 45786 | D37: VIERNES | E37: TU EMPRESA SEGURA | F37: Juan Diego | G37: CLAUDIA PATRICIA MOLINA SANTOS | H37: Cédula de Ciudadanía | I37: 1070989191 | J37: clau300625@hotmail.es | K37: 3132973915 | L37: BORJA FLOWERS SAS | M37: 901546567 | N37: 45786 | O37: 3:55p. m. | P37: 3 | Q37: =IF(OR(P37=1,P37=2,P37=3),106666,IF(OR(P37=4,P37=5),213000,"")) -> 106666 | R37: CONEXIÓN AUTÓNOMA DE ANALISTA | S37: PLANEAR | T37: 0.1 Trabajo autónomo analista en plataforma | U37: =IFERROR(VLOOKUP(T37,PHVA!$B$2:$C$74,2,0),0) -> 0.5 | V37: siendo la hora de conexion el usuario no se presenta, llamo via wassap y telefonicamente, y no recibo respuesta, se envia correo de citacion, se verifica el link y es el dado por el usuario, SE REALIZA FORMATO DE EVALUACION INICIAL, PARA CONTINUAR CON LOS CICLOS DEL P.HV.A | W37: 45807 | X37: =ABS(A37-W37) -> 21 | Y37: =VLOOKUP(M37,Hoja3!$L$2:$X$26,13,0) -> 30 | Z37: ACTIVO
A38: 45793 | D38: VIERNES | E38: TU EMPRESA SEGURA | F38: Juan Diego | G38: CLAUDIA PATRICIA MOLINA SANTOS | H38: Cédula de Ciudadanía | I38: 1070989191 | J38: clau300625@hotmail.es | K38: 3132973915 | L38: BORJA FLOWERS SAS | M38: 901546567 | N38: 45793 | O38: 3:55p. m. | P38: 3 | Q38: =IF(OR(P38=1,P38=2,P38=3),106666,IF(OR(P38=4,P38=5),213000,"")) -> 106666 | R38: SI | S38: PLANEAR | T38: 1.0.3 Navegando en la plataforma y beneficios del programa | U38: =IFERROR(VLOOKUP(T38,PHVA!$B$2:$C$74,2,0),0) -> 1 | V38: se explica programa y se da induccion de la plataforma | W38: 45807 | X38: =ABS(A38-W38) -> 14 | Y38: =VLOOKUP(M38,Hoja3!$L$2:$X$26,13,0) -> 30 | Z38: ACTIVO
A39: 45800 | D39: VIERNES | E39: TU EMPRESA SEGURA | F39: Juan Diego | G39: CLAUDIA PATRICIA MOLINA SANTOS | H39: Cédula de Ciudadanía | I39: 1070989191 | J39: clau300625@hotmail.es | K39: 3132973915 | L39: BORJA FLOWERS SAS | M39: 901546567 | N39: 45797 | O39: 3:55p. m. | P39: 3 | Q39: =IF(OR(P39=1,P39=2,P39=3),106666,IF(OR(P39=4,P39=5),213000,"")) -> 106666 | R39: CONEXIÓN AUTÓNOMA DE ANALISTA | S39: PLANEAR | T39: 0.1 Trabajo autónomo analista en plataforma | U39: =IFERROR(VLOOKUP(T39,PHVA!$B$2:$C$74,2,0),0) -> 0.5 | V39: en la hora indicada se contacta a la persona enlace, me indica que no sera posible reunirse hoy porque esta en obra. | W39: 45807 | X39: =ABS(A39-W39) -> 7 | Y39: =VLOOKUP(M39,Hoja3!$L$2:$X$26,13,0) -> 30 | Z39: ACTIVO
A40: 45797 | D40: MARTES | E40: TU EMPRESA SEGURA | F40: LUZ | G40: CLAUDIA PATRICIA MOLINA SANTOS | H40: Cédula de Ciudadanía | I40: 1070989191 | J40: clau300625@hotmail.es | K40: 3132973915 | L40: BORJA FLOWERS SAS | M40: 901546567 | N40: 45797 | O40: 3:55p. m. | P40: 3 | Q40: =IF(OR(P40=1,P40=2,P40=3),106666,IF(OR(P40=4,P40=5),213000,"")) -> 106666 | R40: NO | S40: PLANEAR | T40: 0. No conexión | U40: =IFERROR(VLOOKUP(T40,PHVA!$B$2:$C$74,2,0),0) -> 0 | V40: No se realizo la conexion por temas de coordinacion con correo . | W40: 45807 | X40: =ABS(A40-W40) -> 10 | Y40: =VLOOKUP(M40,Hoja3!$L$2:$X$26,13,0) -> 30 | Z40: ACTIVO
A41: 45814 | D41: VIERNES | E41: TU EMPRESA SEGURA | F41: Juan Diego | G41: CLAUDIA PATRICIA MOLINA SANTOS | H41: Cédula de Ciudadanía | I41: 1070989191 | J41: clau300625@hotmail.es | K41: 3132973915 | L41: BORJA FLOWERS SAS | M41: 901546567 | N41: 45814 | O41: 3:55p. m. | P41: 3 | Q41: =IF(OR(P41=1,P41=2,P41=3),106666,IF(OR(P41=4,P41=5),213000,"")) -> 106666 | R41: NO | S41: PLANEAR | T41: 1.1.1. Responsable del Sistema de Gestión de Seguridad y Salud en el Trabajo SG-SST | U41: =IFERROR(VLOOKUP(T41,PHVA!$B$2:$C$74,2,0),0) -> 0.5 | V41: Se raliza confirmacion de que debido a que la persona enlace estaba en cmpo no puede acceder a la asesrria, se adelanta asit¿gnacion de responsabilidades | W41: 45807 | X41: =ABS(A41-W41) -> 7 | Y41: =VLOOKUP(M41,Hoja3!$L$2:$X$26,13,0) -> 30 | Z41: ACTIVO
A42: 45804 | D42: MARTES | E42: TU EMPRESA SEGURA | F42: LUZ | G42: CLAUDIA PATRICIA MOLINA SANTOS | H42: Cédula de Ciudadanía | I42: 1070989191 | J42: clau300625@hotmail.es | K42: 3132973915 | L42: BORJA FLOWERS SAS | M42: 901546567 | N42: 45804 | O42: 3:55p. m. | P42: 3 | Q42: =IF(OR(P42=1,P42=2,P42=3),106666,IF(OR(P42=4,P42=5),213000,"")) -> 106666 | R42: CONEXIÓN AUTÓNOMA DE ANALISTA | S42: PLANEAR | T42: 0.1 Trabajo autónomo analista en plataforma | U42: =IFERROR(VLOOKUP(T42,PHVA!$B$2:$C$74,2,0),0) -> 0.5 | V42: No se conecto a la conexion por temas de su agendamiento.olvido la conexion.dice via llamada telefonica. | W42: 45807 | X42: =ABS(A42-W42) -> 3 | Y42: =VLOOKUP(M42,Hoja3!$L$2:$X$26,13,0) -> 30 | Z42: ACTIVO
A43: 45666 | D43: VIERNES | E43: TU EMPRESA SEGURA | F43: LUZ | G43: CLAUDIA PATRICIA MOLINA SANTOS | H43: Cédula de Ciudadanía | I43: 1070989191 | J43: clau300625@hotmail.es | K43: 3132973915 | L43: BORJA FLOWERS SAS | M43: 901546567 | N43: 45811 | O43: 8:05 a. m. | P43: 3 | Q43: =IF(OR(P43=1,P43=2,P43=3),106666,IF(OR(P43=4,P43=5),213000,"")) -> 106666 | R43: CONEXIÓN AUTÓNOMA DE ANALISTA | S43: PLANEAR | T43: 0.1 Trabajo autónomo analista en plataforma | U43: =IFERROR(VLOOKUP(T43,PHVA!$B$2:$C$74,2,0),0) -> 0.5 | V43: llevo junio 3 y 10 que el cliente No se conecta,no responde whatsapp ,ni la llamada telefonica,venia del analista juan | W43: 45807 | X43: =ABS(A43-W43) -> 141 | Y43: =VLOOKUP(M43,Hoja3!$L$2:$X$26,13,0) -> 30 | Z43: ACTIVO
A44: 45717 | B44: MARZO | C44: 3 | D44: JUEVES | E44: TU EMPRESA SEGURA | F44: LUZ | G44: JUBER NEVARDO MARTINEZ GIRALDO | H44: Cédula de Ciudadanía | I44: 1039685226 | J44: adm.car.mc@gmail.com | K44: 3206709930 | L44: CARNES MONTECARLO | M44: 43476587 | N44: 45792 | O44: 1:15 p.m | P44: 3 | Q44: =IF(OR(P44=1,P44=2,P44=3),106666,IF(OR(P44=4,P44=5),213000,"")) -> 106666 | R44: NO | S44: PLANEAR | T44: 1.0.2 Socialización SGSST | U44: =IFERROR(VLOOKUP(T44,PHVA!$B$2:$C$74,2,0),0) -> 2 | V44: Solicita reprogramar reunion para otro dia,teniendo en cuenta que la agenda esta copada ,se le enviara por correo tareas para la proxima conexion. | W44: 45807 | X44: =ABS(A44-W44) -> 90 | Y44: =VLOOKUP(M44,Hoja3!$L$2:$X$26,13,0) -> 4 | Z44: ACTIVO
A45: 45771 | D45: JUEVES | E45: TU EMPRESA SEGURA | F45: LUZ | G45: JUBER NEVARDO MARTINEZ GIRALDO | H45: Cédula de Ciudadanía | I45: 1039685226 | J45: adm.car.mc@gmail.com | K45: 3206709930 | L45: CARNES MONTECARLO | M45: 43476587 | N45: 24/04/2025 | O45: 1:15 p.m | P45: 3 | Q45: =IF(OR(P45=1,P45=2,P45=3),106666,IF(OR(P45=4,P45=5),213000,"")) -> 106666 | R45: SI | S45: PLANEAR | T45: 1.0.1 Firma de Términos y Condiciones | U45: =IFERROR(VLOOKUP(T45,PHVA!$B$2:$C$74,2,0),0) -> 1 | V45: El dia 24 de abril quedamos pendientes de enviarle la contraseña y usuario,se le explica Dara por medio de la plataforma de luz estrada,como es el manejo de la plataforma,donde esta el documento de terminos y condiciones y la importancia de generar los archivos documentales para que sea mas efectivo el diligenciar los documentos. | W45: 45807 | X45: =ABS(A45-W45) -> 36 | Y45: =VLOOKUP(M45,Hoja3!$L$2:$X$26,13,0) -> 4 | Z45: ACTIVO
A46: 45724 | D46: JUEVES | E46: TU EMPRESA SEGURA | F46: LUZ | G46: JUBER NEVARDO MARTINEZ GIRALDO | H46: Cédula de Ciudadanía | I46: 1039685226 | J46: adm.car.mc@gmail.com | K46: 3206709930 | L46: CARNES MONTECARLO | M46: 43476587 | N46: 45799 | O46: 1:15 p.m | P46: 3 | Q46: =IF(OR(P46=1,P46=2,P46=3),106666,IF(OR(P46=4,P46=5),213000,"")) -> 106666 | R46: NO CONEXIÓN | S46: PLANEAR | T46: 0. No conexión | U46: =IFERROR(VLOOKUP(T46,PHVA!$B$2:$C$74,2,0),0) -> 0 | V46: Envia mensaje whatsapp que olvido la conexion. | W46: 45807 | X46: =ABS(A46-W46) -> 83 | Y46: =VLOOKUP(M46,Hoja3!$L$2:$X$26,13,0) -> 4 | Z46: ACTIVO
A47: 45731 | D47: JUEVES | E47: TU EMPRESA SEGURA | F47: LUZ | G47: JUBER NEVARDO MARTINEZ GIRALDO | H47: Cédula de Ciudadanía | I47: 1039685226 | J47: adm.car.mc@gmail.com | K47: 3206709930 | L47: CARNES MONTECARLO | M47: 43476587 | N47: 45806 | O47: 1:15 p.m | P47: 3 | Q47: =IF(OR(P47=1,P47=2,P47=3),106666,IF(OR(P47=4,P47=5),213000,"")) -> 106666 | R47: SI | S47: PLANEAR | T47: 1.0.6 Diagnóstico del Sistema de Gestión de Seguridad y Salud en el Trabajo (SG-SST) 0312 DE 2019 | U47: =IFERROR(VLOOKUP(T47,PHVA!$B$2:$C$74,2,0),0) -> 2 | V47: se realiza evaluacion inicial (Critico)se envia correo de paso a paso para montar registro de afiliacion y documento del perfil. | W47: 45807 | X47: =ABS(A47-W47) -> 76 | Y47: =VLOOKUP(M47,Hoja3!$L$2:$X$26,13,0) -> 4 | Z47: ACTIVO
A48: 45738 | D48: JUEVES | E48: TU EMPRESA SEGURA | F48: LUZ | G48: JUBER NEVARDO MARTINEZ GIRALDO | H48: Cédula de Ciudadanía | I48: 1039685226 | J48: adm.car.mc@gmail.com | K48: 3206709930 | L48: CARNES MONTECARLO | M48: 43476587 | N48: 45813 | O48: 1:15 p.m | P48: 3 | Q48: =IF(OR(P48=1,P48=2,P48=3),106666,IF(OR(P48=4,P48=5),213000,"")) -> 106666 | R48: NO CONEXIÓN | S48: PLANEAR | T48: 0. No conexión | U48: =IFERROR(VLOOKUP(T48,PHVA!$B$2:$C$74,2,0),0) -> 0 | V48: refiere que el dia de hoy no tiene energia y los datos no le dan para la conexion,enviara correo. | W48: 45807 | X48: =ABS(A48-W48) -> 69 | Y48: =VLOOKUP(M48,Hoja3!$L$2:$X$26,13,0) -> 4 | Z48: ACTIVO
A49: 45751 | B49: ABRIL | C49: 2 | D49: VIERNES | E49: TU EMPRESA SEGURA | F49: Juan Diego | G49: MONICA YANETH OCAMPO SERNA | H49: Cédula de Ciudadanía | I49: 1036780830 | J49: floresmundocolores@gmail.com | K49: 3147830285 | L49: CI FLORES MUNDO COLORES SAS | M49: 900509996 | N49: 45751 | O49: 3:05PM | P49: 3 | Q49: =IF(OR(P49=1,P49=2,P49=3),106666,IF(OR(P49=4,P49=5),213000,"")) -> 106666 | R49: SI | S49: PLANEAR | T49: 1.0.0 Bienvenida | U49: =IFERROR(VLOOKUP(T49,PHVA!$B$2:$C$74,2,0),0) -> 1 | V49: el dia viernes 21 de marzo se llamo a la empresa para validar la llegada del correo electronico con el usuario y la contraseña a lo cual indicaron que si les llego y que no han tenido ningun inconveniente | W49: 45807 | X49: =ABS(A49-W49) -> 56 | Y49: =VLOOKUP(M49,Hoja3!$L$2:$X$26,13,0) -> 3 | Z49: ACTIVO
A50: 45758 | D50: VIERNES | E50: TU EMPRESA SEGURA | F50: Juan Diego | G50: MONICA YANETH OCAMPO SERNA | H50: Cédula de Ciudadanía | I50: 1036780830 | J50: floresmundocolores@gmail.com | K50: 3147830285 | L50: CI FLORES MUNDO COLORES SAS | M50: 900509996 | N50: 45758 | O50: 3:05PM | P50: 3 | Q50: =IF(OR(P50=1,P50=2,P50=3),106666,IF(OR(P50=4,P50=5),213000,"")) -> 106666 | R50: SI | S50: PLANEAR | T50: 0.1 Trabajo autónomo analista en plataforma | U50: =IFERROR(VLOOKUP(T50,PHVA!$B$2:$C$74,2,0),0) -> 0.5 | V50: se orgniza la plantilla de evaluacion inicial,con los datos de la empresa, se nicia codificacion | W50: 45807 | X50: =ABS(A50-W50) -> 49 | Y50: =VLOOKUP(M50,Hoja3!$L$2:$X$26,13,0) -> 3 | Z50: ACTIVO
A51: 45765 | D51: VIERNES | E51: TU EMPRESA SEGURA | F51: Juan Diego | G51: MONICA YANETH OCAMPO SERNA | H51: Cédula de Ciudadanía | I51: 1036780830 | J51: floresmundocolores@gmail.com | K51: 3147830285 | L51: CI FLORES MUNDO COLORES SAS | M51: 900509996 | N51: 45765 | O51: 3:05PM | P51: 3 | Q51: =IF(OR(P51=1,P51=2,P51=3),106666,IF(OR(P51=4,P51=5),213000,"")) -> 106666 | R51: CONEXIÓN AUTÓNOMA DE ANALISTA | S51: PLANEAR | T51: 0.1 Trabajo autónomo analista en plataforma | U51: =IFERROR(VLOOKUP(T51,PHVA!$B$2:$C$74,2,0),0) -> 0.5 | V51: serealiza documento de asignacion del responsable, | W51: 45807 | X51: =ABS(A51-W51) -> 42 | Y51: =VLOOKUP(M51,Hoja3!$L$2:$X$26,13,0) -> 3 | Z51: ACTIVO
A52: 45772 | D52: VIERNES | E52: TU EMPRESA SEGURA | F52: Juan Diego | G52: MONICA YANETH OCAMPO SERNA | H52: Cédula de Ciudadanía | I52: 1036780830 | J52: floresmundocolores@gmail.com | K52: 3147830285 | L52: CI FLORES MUNDO COLORES SAS | M52: 900509996 | N52: 45772 | O52: 3:05PM | P52: 3 | Q52: =IF(OR(P52=1,P52=2,P52=3),106666,IF(OR(P52=4,P52=5),213000,"")) -> 106666 | R52: SI | S52: PLANEAR | T52: 1.0.5 Diagnóstico de Madurez | U52: =IFERROR(VLOOKUP(T52,PHVA!$B$2:$C$74,2,0),0) -> 3 | V52: Se solicitan documentos legales y se realiza registro de empleados en plataforma, se revisa la firma y queda adjuntada, se inicia diagnostico d emadurezen plataforma | W52: 45807 | X52: =ABS(A52-W52) -> 35 | Y52: =VLOOKUP(M52,Hoja3!$L$2:$X$26,13,0) -> 3 | Z52: ACTIVO
A53: 45783 | D53: VIERNES | E53: TU EMPRESA SEGURA | F53: Juan Diego | G53: MONICA YANETH OCAMPO SERNA | H53: Cédula de Ciudadanía | I53: 1036780830 | J53: floresmundocolores@gmail.com | K53: 3147830285 | L53: CI FLORES MUNDO COLORES SAS | M53: 900509996 | N53: 45783 | O53: 3:05PM | P53: 3 | Q53: =IF(OR(P53=1,P53=2,P53=3),106666,IF(OR(P53=4,P53=5),213000,"")) -> 106666 | R53: NO | S53: PLANEAR | T53: 1.0.9 Savanna Ruta de Bienestar | U53: =IFERROR(VLOOKUP(T53,PHVA!$B$2:$C$74,2,0),0) -> 4 | V53: no se realiza conexion via internet, por fallas en la red potr aprte del cliente, se da instruccion via telefonica de registrar los empleados en plataforma, y como hacerlo | W53: 45807 | X53: =ABS(A53-W53) -> 24 | Y53: =VLOOKUP(M53,Hoja3!$L$2:$X$26,13,0) -> 3 | Z53: ACTIVO
A54: 45779 | D54: VIERNES | E54: TU EMPRESA SEGURA | F54: Juan Diego | G54: MONICA YANETH OCAMPO SERNA | H54: Cédula de Ciudadanía | I54: 1036780830 | J54: floresmundocolores@gmail.com | K54: 3147830285 | L54: CI FLORES MUNDO COLORES SAS | M54: 900509996 | N54: 45779 | O54: 3:05PM | P54: 3 | Q54: =IF(OR(P54=1,P54=2,P54=3),106666,IF(OR(P54=4,P54=5),213000,"")) -> 106666 | R54: NO | S54: PLANEAR | T54: 1.0.2 Socialización SGSST | U54: =IFERROR(VLOOKUP(T54,PHVA!$B$2:$C$74,2,0),0) -> 2 | V54: no se realiza conexion via internet, por fallas en la red potr aprte del cliente, se da instruccion via telefonica de registrar los empleados en plataforma, y como hacerlo | W54: 45807 | X54: =ABS(A54-W54) -> 28 | Y54: =VLOOKUP(M54,Hoja3!$L$2:$X$26,13,0) -> 3 | Z54: ACTIVO
A55: 45793 | D55: VIERNES | E55: TU EMPRESA SEGURA | F55: LUZ | G55: MONICA YANETH OCAMPO SERNA | H55: Cédula de Ciudadanía | I55: 1036780830 | J55: floresmundocolores@gmail.com | K55: 3147830285 | L55: CI FLORES MUNDO COLORES SAS | M55: 900509996 | N55: 45790 | O55: 9:00AM | P55: 3 | Q55: =IF(OR(P55=1,P55=2,P55=3),106666,IF(OR(P55=4,P55=5),213000,"")) -> 106666 | R55: SI | S55: PLANEAR | T55: 1.0.1 Firma de Términos y Condiciones | U55: =IFERROR(VLOOKUP(T55,PHVA!$B$2:$C$74,2,0),0) -> 1 | V55: Se revisa terminos y condiciones,se le solicita logo de la empresa,se diligencia documento de responsable sst,se digitan 15 documentos de ejemplo para archivo documental,se le envia correo de paso a paso para diligenciar documento perfilsociodemografico y como subir documentos del numeral 1.1.4. | W55: 45807 | X55: =ABS(A55-W55) -> 14 | Y55: =VLOOKUP(M55,Hoja3!$L$2:$X$26,13,0) -> 3 | Z55: ACTIVO
A56: 45800 | D56: VIERNES | E56: TU EMPRESA SEGURA | F56: LUZ | G56: MONICA YANETH OCAMPO SERNA | H56: Cédula de Ciudadanía | I56: 1036780830 | J56: floresmundocolores@gmail.com | K56: 3147830285 | L56: CI FLORES MUNDO COLORES SAS | M56: 900509996 | N56: 45797 | O56: 3:05PM | P56: 3 | Q56: =IF(OR(P56=1,P56=2,P56=3),106666,IF(OR(P56=4,P56=5),213000,"")) -> 106666 | R56: SI | S56: PLANEAR | T56: 1.1.1. Responsable del Sistema de Gestión de Seguridad y Salud en el Trabajo SG-SST | U56: =IFERROR(VLOOKUP(T56,PHVA!$B$2:$C$74,2,0),0) -> 0.5 | V56: Se sube el logo a la plataforma,severifica el perfilsociodemografico,firma de responsabilidad y funciones del SG-SST ,Proxima reunion serrealizara evaluacion inicial y documento de terminos y condiciones. | W56: 45807 | X56: =ABS(A56-W56) -> 7 | Y56: =VLOOKUP(M56,Hoja3!$L$2:$X$26,13,0) -> 3 | Z56: ACTIVO
A57: 45800 | D57: VIERNES | E57: TU EMPRESA SEGURA | F57: LUZ | G57: MONICA YANETH OCAMPO SERNA | H57: Cédula de Ciudadanía | I57: 1036780830 | J57: floresmundocolores@gmail.com | K57: 3147830285 | L57: CI FLORES MUNDO COLORES SAS | M57: 900509996 | N57: 45797 | O57: 3:05PM | P57: 3 | Q57: =IF(OR(P57=1,P57=2,P57=3),106666,IF(OR(P57=4,P57=5),213000,"")) -> 106666 | R57: SI | S57: PLANEAR | T57: 1.1.2 Responsabilidades en el Sistema de Gestión de Seguridad y Salud en el Trabajo – SG-SST | U57: =IFERROR(VLOOKUP(T57,PHVA!$B$2:$C$74,2,0),0) -> 0.5 | V57: Se sube el logo a la plataforma,severifica el perfilsociodemografico,firma de responsabilidad y funciones del SG-SST ,Proxima reunion serrealizara evaluacion inicial y documento de terminos y condiciones. | W57: 45807 | X57: =ABS(A57-W57) -> 7 | Y57: =VLOOKUP(M57,Hoja3!$L$2:$X$26,13,0) -> 3 | Z57: ACTIVO
A58: 45807 | D58: VIERNES | E58: TU EMPRESA SEGURA | F58: LUZ | G58: MONICA YANETH OCAMPO SERNA | H58: Cédula de Ciudadanía | I58: 1036780830 | J58: floresmundocolores@gmail.com | K58: 3147830285 | L58: CI FLORES MUNDO COLORES SAS | M58: 900509996 | N58: 45804 | O58: 0.375 | P58: 3 | Q58: =IF(OR(P58=1,P58=2,P58=3),106666,IF(OR(P58=4,P58=5),213000,"")) -> 106666 | R58: SI | S58: PLANEAR | T58: 1.0.6 Diagnóstico del Sistema de Gestión de Seguridad y Salud en el Trabajo (SG-SST) 0312 DE 2019 | U58: =IFERROR(VLOOKUP(T58,PHVA!$B$2:$C$74,2,0),0) -> 2 | V58: Se firma terminos y condiciones,envio pdf y se realiza evaluacion inicicial (critico) | W58: 45807 | X58: =ABS(A58-W58) -> 0 | Y58: =VLOOKUP(M58,Hoja3!$L$2:$X$26,13,0) -> 3 | Z58: ACTIVO
A59: 45814 | D59: VIERNES | E59: TU EMPRESA SEGURA | F59: LUZ | G59: MONICA YANETH OCAMPO SERNA | H59: Cédula de Ciudadanía | I59: 1036780830 | J59: floresmundocolores@gmail.com | K59: 3147830285 | L59: CI FLORES MUNDO COLORES SAS | M59: 900509996 | N59: 45811 | O59: 0.375 | P59: 3 | Q59: =IF(OR(P59=1,P59=2,P59=3),106666,IF(OR(P59=4,P59=5),213000,"")) -> 106666 | R59: SI | S59: PLANEAR | T59: 1.0.4 Acompañamiiento/Asesoría sobre SGSST | U59: =IFERROR(VLOOKUP(T59,PHVA!$B$2:$C$74,2,0),0) -> 2 | V59: Se realiza revision del hacer esta diligenciado pero la señora monica manifiesta que nunca lo a realizado,porque no recuerda como se hace,se le notifica el procedimiento de la politica y por temas de tiempo en su conexion no se logro realizar el cronograma. | W59: 45807 | X59: =ABS(A59-W59) -> 7 | Y59: =VLOOKUP(M59,Hoja3!$L$2:$X$26,13,0) -> 3 | Z59: ACTIVO
A60: 45793 | D60: VIERNES | E60: TU EMPRESA SEGURA | F60: Juan Diego | G60: MONICA YANETH OCAMPO SERNA | H60: Cédula de Ciudadanía | I60: 1036780830 | J60: floresmundocolores@gmail.com | K60: 3147830285 | L60: CI FLORES MUNDO COLORES SAS | M60: 900509996 | N60: 45793 | O60: 8:05-8:50AM | P60: 3 | Q60: =IF(OR(P60=1,P60=2,P60=3),106666,IF(OR(P60=4,P60=5),213000,"")) -> 106666 | R60: CONEXIÓN AUTÓNOMA DE ANALISTA | S60: PLANEAR | T60: 0.1 Trabajo autónomo analista en plataforma | U60: =IFERROR(VLOOKUP(T60,PHVA!$B$2:$C$74,2,0),0) -> 0.5 | V60: se inicia con la codificacion | W60: 45807 | X60: =ABS(A60-W60) -> 14 | Y60: =VLOOKUP(M60,Hoja3!$L$2:$X$26,13,0) -> 3 | Z60: ACTIVO
A61: 45751 | B61: ABRIL | C61: 2 | D61: VIERNES | E61: TU EMPRESA SEGURA | F61: Cristhian | G61: Jorge ignacio Martínez García | H61: Cédula de Ciudadanía | I61: 70952794 | J61: j73jimg@hotmail.com | K61: 3216422617 | L61: EMTURPE LIMITADA | M61: 900112921 | N61: 45751 | O61: 7:15a. m. | P61: 4 | Q61: =IF(OR(P61=1,P61=2,P61=3),106666,IF(OR(P61=4,P61=5),213000,"")) -> 213000 | R61: SI | S61: PLANEAR | T61: 1.0.0 Bienvenida | U61: =IFERROR(VLOOKUP(T61,PHVA!$B$2:$C$74,2,0),0) -> 1 | V61: se realiza la reunion de bienvenida pero en la mitad de la reunion se tuvieron problemas de connexion por lo cual se finaliza la misma | W61: 45807 | X61: =ABS(A61-W61) -> 56 | Y61: =VLOOKUP(M61,Hoja3!$L$2:$X$26,13,0) -> 5 | Z61: ACTIVO
A62: 45758 | D62: VIERNES | E62: TU EMPRESA SEGURA | F62: Cristhian | G62: Jorge ignacio Martínez García | H62: Cédula de Ciudadanía | I62: 70952794 | J62: j73jimg@hotmail.com | K62: 3216422617 | L62: EMTURPE LIMITADA | M62: 900112921 | N62: 45758 | O62: 7:15a. m. | P62: 4 | Q62: =IF(OR(P62=1,P62=2,P62=3),106666,IF(OR(P62=4,P62=5),213000,"")) -> 213000 | R62: NO | S62: PLANEAR | T62: 0. No participación de empresa | U62: =IFERROR(VLOOKUP(T62,PHVA!$B$2:$C$74,2,0),0) -> 0 | V62: no se realiza conexión por que el señor encargado no se conecto al encuentro | W62: 45807 | X62: =ABS(A62-W62) -> 49 | Y62: =VLOOKUP(M62,Hoja3!$L$2:$X$26,13,0) -> 5 | Z62: ACTIVO
A63: 45765 | D63: VIERNES | E63: TU EMPRESA SEGURA | F63: Juan Diego | G63: Jorge ignacio Martínez García | H63: Cédula de Ciudadanía | I63: 70952794 | J63: j73jimg@hotmail.com | K63: 3216422617 | L63: EMTURPE LIMITADA | M63: 900112921 | N63: 45765 | O63: 7:15a. m. | P63: 4 | Q63: =IF(OR(P63=1,P63=2,P63=3),106666,IF(OR(P63=4,P63=5),213000,"")) -> 213000 | R63: NO | S63: PLANEAR | T63: 0. No participación de empresa | U63: =IFERROR(VLOOKUP(T63,PHVA!$B$2:$C$74,2,0),0) -> 0 | V63: no se realiza conexión por que era viernes de semana sanrta | W63: 45807 | X63: =ABS(A63-W63) -> 42 | Y63: =VLOOKUP(M63,Hoja3!$L$2:$X$26,13,0) -> 5 | Z63: ACTIVO
A64: 45776 | D64: VIERNES | E64: TU EMPRESA SEGURA | F64: Juan Diego | G64: Jorge ignacio Martínez García | H64: Cédula de Ciudadanía | I64: 70952794 | J64: j73jimg@hotmail.com | K64: 3216422617 | L64: EMTURPE LIMITADA | M64: 900112921 | N64: 45776 | O64: 7:15a. m. | P64: 4 | Q64: =IF(OR(P64=1,P64=2,P64=3),106666,IF(OR(P64=4,P64=5),213000,"")) -> 213000 | R64: SI | S64: PLANEAR | T64: 1.0.9 Savanna Ruta de Bienestar | U64: =IFERROR(VLOOKUP(T64,PHVA!$B$2:$C$74,2,0),0) -> 4 | W64: 45807 | X64: =ABS(A64-W64) -> 31 | Y64: =VLOOKUP(M64,Hoja3!$L$2:$X$26,13,0) -> 5 | Z64: ACTIVO
A65: 45772 | D65: VIERNES | E65: TU EMPRESA SEGURA | F65: Juan Diego | G65: Jorge ignacio Martínez García | H65: Cédula de Ciudadanía | I65: 70952794 | J65: j73jimg@hotmail.com | K65: 3216422617 | L65: EMTURPE LIMITADA | M65: 900112921 | N65: 45772 | O65: 7:15a. m. | P65: 4 | Q65: =IF(OR(P65=1,P65=2,P65=3),106666,IF(OR(P65=4,P65=5),213000,"")) -> 213000 | R65: SI | S65: PLANEAR | T65: 1.0.6 Diagnóstico del Sistema de Gestión de Seguridad y Salud en el Trabajo (SG-SST) 0312 DE 2019 | U65: =IFERROR(VLOOKUP(T65,PHVA!$B$2:$C$74,2,0),0) -> 2 | V65: S hace presentacion de analista y de la plataforma Sistegra, se Solicitan documentos legales: RUT, Documento delgerente, camara de comercio, dos ultimos pagos de seguridad social, examenes medicos(pendientes por realizar), se solicita carta de afilizacion a la ARL | W65: 45807 | X65: =ABS(A65-W65) -> 35 | Y65: =VLOOKUP(M65,Hoja3!$L$2:$X$26,13,0) -> 5 | Z65: ACTIVO
A66: 45779 | D66: VIERNES | E66: TU EMPRESA SEGURA | F66: Juan Diego | G66: Jorge ignacio Martínez García | H66: Cédula de Ciudadanía | I66: 70952794 | J66: j73jimg@hotmail.com | K66: 3216422617 | L66: EMTURPE LIMITADA | M66: 900112921 | N66: 45779 | O66: 7:15a. m. | P66: 4 | Q66: =IF(OR(P66=1,P66=2,P66=3),106666,IF(OR(P66=4,P66=5),213000,"")) -> 213000 | R66: NO | S66: PLANEAR | T66: 0. No participación de empresa | U66: =IFERROR(VLOOKUP(T66,PHVA!$B$2:$C$74,2,0),0) -> 0 | V66: el dos de mayo, no se reporta conexion a la hora establecida, 15 minutos antes llamo al contactto que esat en la base de datos compartida, via wassap, telefono y no hay respeusta, espero hasta las 7:26 am | W66: 45807 | X66: =ABS(A66-W66) -> 28 | Y66: =VLOOKUP(M66,Hoja3!$L$2:$X$26,13,0) -> 5 | Z66: ACTIVO
A67: 45786 | D67: VIERNES | E67: TU EMPRESA SEGURA | F67: Juan Diego | G67: Jorge ignacio Martínez García | H67: Cédula de Ciudadanía | I67: 70952794 | J67: j73jimg@hotmail.com | K67: 3216422617 | L67: EMTURPE LIMITADA | M67: 900112921 | N67: 45786 | O67: 7:15a. m. | P67: 4 | Q67: =IF(OR(P67=1,P67=2,P67=3),106666,IF(OR(P67=4,P67=5),213000,"")) -> 213000 | R67: SI | S67: PLANEAR | T67: 1.0.1 Firma de Términos y Condiciones | U67: =IFERROR(VLOOKUP(T67,PHVA!$B$2:$C$74,2,0),0) -> 1 | V67: se revisa usuario y contraseña en plataforma y se resuelven dudas frente al programa tu empresa segura, se revisa terminos y condiciones y esta al dia, quedamos en enviar examenes médicos y otra documentacion de soporte legal al analista, ya que, no tienen examenes médicos ocupacionales | W67: 45807 | X67: =ABS(A67-W67) -> 21 | Y67: =VLOOKUP(M67,Hoja3!$L$2:$X$26,13,0) -> 5 | Z67: ACTIVO
A68: 45793 | D68: VIERNES | E68: TU EMPRESA SEGURA | F68: Juan Diego | G68: Jorge ignacio Martínez García | H68: Cédula de Ciudadanía | I68: 70952794 | J68: j73jimg@hotmail.com | K68: 3216422617 | L68: EMTURPE LIMITADA | M68: 900112921 | N68: 45793 | O68: 7:15a. m. | P68: 4 | Q68: =IF(OR(P68=1,P68=2,P68=3),106666,IF(OR(P68=4,P68=5),213000,"")) -> 213000 | R68: SI | S68: PLANEAR | T68: 1.0.3 Navegando en la plataforma y beneficios del programa | U68: =IFERROR(VLOOKUP(T68,PHVA!$B$2:$C$74,2,0),0) -> 1 | V68: se solicita nuevamente la realizacion de los examenes medicos ocupacionales, se verifica firma de terminos y condiciones y se da un panorama orientador del programa tue empresa segura y de la plataforma | W68: 45807 | X68: =ABS(A68-W68) -> 14 | Y68: =VLOOKUP(M68,Hoja3!$L$2:$X$26,13,0) -> 5 | Z68: ACTIVO
A69: 45800 | D69: VIERNES | E69: TU EMPRESA SEGURA | F69: Juan Diego | G69: Jorge ignacio Martínez García | H69: Cédula de Ciudadanía | I69: 70952794 | J69: j73jimg@hotmail.com | K69: 3216422617 | L69: EMTURPE LIMITADA | M69: 900112921 | N69: 45800 | O69: 7:15a. m. | P69: 4 | Q69: =IF(OR(P69=1,P69=2,P69=3),106666,IF(OR(P69=4,P69=5),213000,"")) -> 213000 | R69: SI | S69: PLANEAR | T69: 1.1.1. Responsable del Sistema de Gestión de Seguridad y Salud en el Trabajo SG-SST | U69: =IFERROR(VLOOKUP(T69,PHVA!$B$2:$C$74,2,0),0) -> 0.5 | V69: Se inicia con la asigacion del responsable en la plataforma, y se informa que se estan adelantando examenes medicos solicitados | W69: 45807 | X69: =ABS(A69-W69) -> 7 | Y69: =VLOOKUP(M69,Hoja3!$L$2:$X$26,13,0) -> 5 | Z69: ACTIVO
A70: 45807 | D70: VIERNES | E70: TU EMPRESA SEGURA | F70: Juan Diego | G70: Jorge ignacio Martínez García | H70: Cédula de Ciudadanía | I70: 70952794 | J70: j73jimg@hotmail.com | K70: 3216422617 | L70: EMTURPE LIMITADA | M70: 900112921 | N70: 45807 | O70: 7:15a. m. | P70: 4 | Q70: =IF(OR(P70=1,P70=2,P70=3),106666,IF(OR(P70=4,P70=5),213000,"")) -> 213000 | R70: SI | S70: PLANEAR | T70: 1.1.4 Afiliación al Sistema General de Riesgos Laborales | U70: =IFERROR(VLOOKUP(T70,PHVA!$B$2:$C$74,2,0),0) -> 0.5 | V70: se consulta sobre el estado de la capacitacion en equipos de emergencia, ya que el Sr.tenia dudas sobre el tipo de extintores para su empresa, se adelanta diligenciamiento de asignacion del responsable y recibo de planillas de seguridad social | W70: 45807 | X70: =ABS(A70-W70) -> 0 | Y70: =VLOOKUP(M70,Hoja3!$L$2:$X$26,13,0) -> 5 | Z70: ACTIVO
A71: 45814 | D71: VIERNES | E71: TU EMPRESA SEGURA | F71: Juan Diego | G71: Jorge ignacio Martínez García | H71: Cédula de Ciudadanía | I71: 70952794 | J71: j73jimg@hotmail.com | K71: 3216422617 | L71: EMTURPE LIMITADA | M71: 900112921 | N71: 45814 | O71: 7:15a. m. | P71: 4 | Q71: =IF(OR(P71=1,P71=2,P71=3),106666,IF(OR(P71=4,P71=5),213000,"")) -> 213000 | R71: SI | S71: PLANEAR | T71: 1.1.2 Responsabilidades en el Sistema de Gestión de Seguridad y Salud en el Trabajo – SG-SST | U71: =IFERROR(VLOOKUP(T71,PHVA!$B$2:$C$74,2,0),0) -> 0.5 | V71: Se realiza registro de empleados, asignacion de responsabilidades | W71: 45807 | X71: =ABS(A71-W71) -> 7 | Y71: =VLOOKUP(M71,Hoja3!$L$2:$X$26,13,0) -> 5 | Z71: ACTIVO
A72: 45793 | D72: VIERNES | E72: TU EMPRESA SEGURA | F72: Juan Diego | G72: Jorge ignacio Martínez García | H72: Cédula de Ciudadanía | I72: 70952794 | J72: j73jimg@hotmail.com | K72: 3216422617 | L72: EMTURPE LIMITADA | M72: 900112921 | N72: 45793 | Q72: =IF(OR(P72=1,P72=2,P72=3),106666,IF(OR(P72=4,P72=5),213000,"")) | R72: SI | S72: PLANEAR | T72: 0.1 Trabajo autónomo analista en plataforma | U72: =IFERROR(VLOOKUP(T72,PHVA!$B$2:$C$74,2,0),0) -> 0.5 | V72: se realiza codificacion de documentos | W72: 45807 | X72: =ABS(A72-W72) -> 14 | Y72: =VLOOKUP(M72,Hoja3!$L$2:$X$26,13,0) -> 5 | Z72: ACTIVO
A73: 45797 | B73: MAYO | C73: 1 | D73: MARTES | E73: TU EMPRESA SEGURA | F73: LUZ | K73: 3104997696 | L73: ESTRUCTURAS METALICAS DEL CHOCO | M73: 900530803 | N73: 45797 | O73: 10:40 a.m | P73: 3 | Q73: =IF(OR(P73=1,P73=2,P73=3),106666,IF(OR(P73=4,P73=5),213000,"")) -> 106666 | R73: SI | S73: PLANEAR | T73: 1.0.0 Bienvenida | U73: =IFERROR(VLOOKUP(T73,PHVA!$B$2:$C$74,2,0),0) -> 1 | V73: Bienvenida al programa, No firmo firma de termminos y condiciones por temas de no tener contraseña y usuario,se le presenta el programa .se le realiza evaluacion inicial | W73: 45807 | X73: =ABS(A73-W73) -> 10 | Y73: =VLOOKUP(M73,Hoja3!$L$2:$X$26,13,0) -> #N/A | Z73: ACTIVO
A74: 45797 | B74: MAYO | C74: 1 | D74: MARTES | E74: TU EMPRESA SEGURA | F74: LUZ | G74: Kerly Andrea Ortiz Ramirez | H74: Cédula de Ciudadanía | I74: 1128395305 | J74: Kerlyandreaortiz1407@gmail.com | K74: 3128926799 | L74: FOTO SCANNER | M74: 1128395305 | N74: 45797 | O74: 1:00 p.m | P74: 1 | Q74: =IF(OR(P74=1,P74=2,P74=3),106666,IF(OR(P74=4,P74=5),213000,"")) -> 106666 | R74: SI | S74: PLANEAR | T74: 1.0.0 Bienvenida | U74: =IFERROR(VLOOKUP(T74,PHVA!$B$2:$C$74,2,0),0) -> 1 | V74: Se realiza bienvenida, no firmo firma de termminos y condiciones por temas de no tener contraseña y usuario,se le presenta el programa . | W74: 45807 | X74: =ABS(A74-W74) -> 10 | Y74: =VLOOKUP(M74,Hoja3!$L$2:$X$26,13,0) -> 3 | Z74: ACTIVO
A75: 45804 | D75: MARTES | E75: TU EMPRESA SEGURA | F75: LUZ | G75: Kerly Andrea Ortiz Ramirez | H75: Cédula de Ciudadanía | I75: 1128395305 | J75: Kerlyandreaortiz1407@gmail.com | K75: 3128926799 | L75: FOTO SCANNER | M75: 1128395305 | N75: 45804 | O75: 1:15 p.m | P75: 1 | Q75: =IF(OR(P75=1,P75=2,P75=3),106666,IF(OR(P75=4,P75=5),213000,"")) -> 106666 | R75: SI | S75: PLANEAR | T75: 1.0.3 Navegando en la plataforma y beneficios del programa | U75: =IFERROR(VLOOKUP(T75,PHVA!$B$2:$C$74,2,0),0) -> 1 | V75: se realiza explicacion de la plataforma,se explica el numeral 1.1.4 y 2.5.1 .ya que se conecto 25 minutos luego no se pudo reaalizar la evauzaion inicial. | W75: 45807 | X75: =ABS(A75-W75) -> 3 | Y75: =VLOOKUP(M75,Hoja3!$L$2:$X$26,13,0) -> 3 | Z75: ACTIVO
A76: 45811 | D76: MARTES | E76: TU EMPRESA SEGURA | F76: LUZ | G76: Kerly Andrea Ortiz Ramirez | H76: Cédula de Ciudadanía | I76: 1128395305 | J76: Kerlyandreaortiz1407@gmail.com | K76: 3128926799 | L76: FOTO SCANNER | M76: 1128395305 | N76: 45811 | O76: 1:15 p.m | P76: 1 | Q76: =IF(OR(P76=1,P76=2,P76=3),106666,IF(OR(P76=4,P76=5),213000,"")) -> 106666 | R76: SI | S76: PLANEAR | T76: 2.5.1 Archivo o retención documental del Sistema de Gestión en Seguridad y Salud en el Trabajo SG-SST | U76: =IFERROR(VLOOKUP(T76,PHVA!$B$2:$C$74,2,0),0) -> 2 | V76: se firma terminos y condiciones,envia el PDF,se adelanta numeral 2.5.1. | W76: 45807 | X76: =ABS(A76-W76) -> 4 | Y76: =VLOOKUP(M76,Hoja3!$L$2:$X$26,13,0) -> 3 | Z76: ACTIVO
A77: 45775 | B77: ABRIL | C77: 2 | D77: VIERNES | E77: TU EMPRESA SEGURA | F77: Cristhian | G77: LUISA GARCIA | H77: Cédula de Ciudadanía | I77: 1036929374 | J77: luisayepes02@gmail.com | K77: 3194892497 | L77: HYDRANFLOWERS S.A.S | M77: 901166099 | N77: 46133 | O77: 11:00a. m. | P77: 2 | Q77: =IF(OR(P77=1,P77=2,P77=3),106666,IF(OR(P77=4,P77=5),213000,"")) -> 106666 | R77: SI | S77: PLANEAR | T77: 1.0.0 Bienvenida | U77: =IFERROR(VLOOKUP(T77,PHVA!$B$2:$C$74,2,0),0) -> 1 | V77: Bienvenida al programa, se le explica detalladamente en que consiste y la duración estimada, se Indica cómo firmar los términos y condiciones, se agenda la reunión periódica, semanal, los viernes de 3:00 a 3:45pm, se actualiza el correo de contacto: claoarbo@hotmail.com | W77: 45807 | X77: =ABS(A77-W77) -> 32 | Y77: =VLOOKUP(M77,Hoja3!$L$2:$X$26,13,0) -> 7 | Z77: ACTIVO
A78: 45782 | D78: VIERNES | E78: TU EMPRESA SEGURA | F78: Cristhian | G78: LUISA GARCIA | H78: Cédula de Ciudadanía | I78: 1036929374 | J78: luisayepes02@gmail.com | K78: 3194892497 | L78: HYDRANFLOWERS S.A.S | M78: 901166099 | N78: 46140 | O78: 3:00PM | P78: 2 | Q78: =IF(OR(P78=1,P78=2,P78=3),106666,IF(OR(P78=4,P78=5),213000,"")) -> 106666 | R78: NO | S78: PLANEAR | T78: 0. No conexión | U78: =IFERROR(VLOOKUP(T78,PHVA!$B$2:$C$74,2,0),0) -> 0 | V78: No hubo conexión | W78: 45807 | X78: =ABS(A78-W78) -> 25 | Y78: =VLOOKUP(M78,Hoja3!$L$2:$X$26,13,0) -> 7 | Z78: ACTIVO
A79: 45789 | D79: VIERNES | E79: TU EMPRESA SEGURA | F79: Cristhian | G79: LUISA GARCIA | H79: Cédula de Ciudadanía | I79: 1036929374 | J79: luisayepes02@gmail.com | K79: 3194892497 | L79: HYDRANFLOWERS S.A.S | M79: 901166099 | N79: 45758 | O79: 3:00PM | P79: 2 | Q79: =IF(OR(P79=1,P79=2,P79=3),106666,IF(OR(P79=4,P79=5),213000,"")) -> 106666 | R79: NO CONEXIÓN | S79: PLANEAR | T79: 0. No conexión | U79: =IFERROR(VLOOKUP(T79,PHVA!$B$2:$C$74,2,0),0) -> 0 | W79: 45807 | X79: =ABS(A79-W79) -> 18 | Y79: =VLOOKUP(M79,Hoja3!$L$2:$X$26,13,0) -> 7 | Z79: ACTIVO
A80: 45786 | D80: VIERNES | E80: TU EMPRESA SEGURA | F80: JUAN DIEGO | G80: LUISA GARCIA | H80: Cédula de Ciudadanía | I80: 1036929374 | J80: luisayepes02@gmail.com | K80: 3194892497 | L80: HYDRANFLOWERS S.A.S | M80: 901166099 | N80: 45765 | O80: 3:00PM | P80: 2 | Q80: =IF(OR(P80=1,P80=2,P80=3),106666,IF(OR(P80=4,P80=5),213000,"")) -> 106666 | R80: SI | S80: PLANEAR | T80: 1.0.3 Navegando en la plataforma y beneficios del programa | U80: =IFERROR(VLOOKUP(T80,PHVA!$B$2:$C$74,2,0),0) -> 1 | V80: se da un panorama orientador de la plataforma, se explica en que consiste el sgsst y el programa tu empresa segura, se empieza registro de usuarios y administradores en plataforma | W80: 45807 | X80: =ABS(A80-W80) -> 21 | Y80: =VLOOKUP(M80,Hoja3!$L$2:$X$26,13,0) -> 7 | Z80: ACTIVO
A81: 45817 | D81: VIERNES | E81: TU EMPRESA SEGURA | F81: JUAN DIEGO | G81: LUISA GARCIA | H81: Cédula de Ciudadanía | I81: 1036929374 | J81: luisayepes02@gmail.com | K81: 3194892497 | L81: HYDRANFLOWERS S.A.S | M81: 901166099 | N81: 45786 | O81: 0.60069444 | P81: 2 | Q81: =IF(OR(P81=1,P81=2,P81=3),106666,IF(OR(P81=4,P81=5),213000,"")) -> 106666 | R81: SI | S81: PLANEAR | T81: 1.0.3 Navegando en la plataforma y beneficios del programa | U81: =IFERROR(VLOOKUP(T81,PHVA!$B$2:$C$74,2,0),0) -> 1 | V81: se hace solicitud de documentos de la empresa: Rut, camara de comercio, ultimos dos pagos de planilla de seg. social, logotipo de la empresa; se inicia con el registro de usuarios y administradores | W81: 45807 | X81: =ABS(A81-W81) -> 10 | Y81: =VLOOKUP(M81,Hoja3!$L$2:$X$26,13,0) -> 7 | Z81: ACTIVO
A82: 45824 | D82: VIERNES | E82: TU EMPRESA SEGURA | F82: JUAN DIEGO | G82: LUISA GARCIA | H82: Cédula de Ciudadanía | I82: 1036929374 | J82: luisayepes02@gmail.com | K82: 3194892497 | L82: HYDRANFLOWERS S.A.S | M82: 901166099 | N82: 45793 | O82: 0.60069444 | P82: 2 | Q82: =IF(OR(P82=1,P82=2,P82=3),106666,IF(OR(P82=4,P82=5),213000,"")) -> 106666 | R82: SI | S82: PLANEAR | T82: 1.0.6 Diagnóstico del Sistema de Gestión de Seguridad y Salud en el Trabajo (SG-SST) 0312 DE 2019 | U82: =IFERROR(VLOOKUP(T82,PHVA!$B$2:$C$74,2,0),0) -> 2 | V82: se se solicitam y se envia documentos de seg. social, y documentos del sistema de gestion, se explica mas a profundiad el programa tu empresa segura, por dudas del cliente | W82: 45807 | X82: =ABS(A82-W82) -> 17 | Y82: =VLOOKUP(M82,Hoja3!$L$2:$X$26,13,0) -> 7 | Z82: ACTIVO
A83: 45831 | D83: VIERNES | E83: TU EMPRESA SEGURA | F83: JUAN DIEGO | G83: LUISA GARCIA | H83: Cédula de Ciudadanía | I83: 1036929374 | J83: luisayepes02@gmail.com | K83: 3194892497 | L83: HYDRANFLOWERS S.A.S | M83: 901166099 | N83: 45800 | O83: 0.60069444 | P83: 2 | Q83: =IF(OR(P83=1,P83=2,P83=3),106666,IF(OR(P83=4,P83=5),213000,"")) -> 106666 | R83: NO | S83: PLANEAR | T83: 0. No conexión | U83: =IFERROR(VLOOKUP(T83,PHVA!$B$2:$C$74,2,0),0) -> 0 | V83: se contacta en lahora indicada y la persona enlace, me indica que se leha dificultado ingresar,le nevio ellink de teamas y no recibo respuesta | W83: 45807 | X83: =ABS(A83-W83) -> 24 | Y83: =VLOOKUP(M83,Hoja3!$L$2:$X$26,13,0) -> 7 | Z83: ACTIVO
A84: 45800 | D84: VIERNES | E84: TU EMPRESA SEGURA | F84: JUAN DIEGO | G84: LUISA GARCIA | H84: Cédula de Ciudadanía | I84: 1036929374 | J84: luisayepes02@gmail.com | K84: 3194892497 | L84: HYDRANFLOWERS S.A.S | M84: 901166099 | N84: 45800 | O84: 1:15 p.m | P84: 2 | Q84: =IF(OR(P84=1,P84=2,P84=3),106666,IF(OR(P84=4,P84=5),213000,"")) -> 106666 | R84: NO | S84: PLANEAR | T84: 1.1.1. Responsable del Sistema de Gestión de Seguridad y Salud en el Trabajo SG-SST | U84: =IFERROR(VLOOKUP(T84,PHVA!$B$2:$C$74,2,0),0) -> 0.5 | V84: Se contacta por via wassap y telefonica y no se recibe respuesta, se adelanta revision de asignaicon de responsabilidades | W84: 45807 | X84: =ABS(A84-W84) -> 7 | Y84: =VLOOKUP(M84,Hoja3!$L$2:$X$26,13,0) -> 7 | Z84: ACTIVO
A85: 45741 | B85: MARZO | C85: 3 | D85: MARTES | E85: TU EMPRESA SEGURA | F85: LUZ | G85: LIANA OCAMPO | H85: Cédula de Ciudadanía | I85: 1036778480 | J85: Locampo@picados.com.co | K85: 3127198417 | L85: INVERSIONES VALLEJUELO S.A.S. | M85: 900655932 | N85: 45741 | O85: 0.45833333 | P85: 3 | Q85: =IF(OR(P85=1,P85=2,P85=3),106666,IF(OR(P85=4,P85=5),213000,"")) -> 106666 | R85: SI | S85: PLANEAR | T85: 1.0.0 Bienvenida | U85: =IFERROR(VLOOKUP(T85,PHVA!$B$2:$C$74,2,0),0) -> 1 | V85: el dia viernes 21 de marzo se llamo a la empresa para validar la llegada del correo electronico con el usuario y la contraseña a lo cual indicaron que si les llego y que no han tenido ningun inconveniente | W85: 45807 | X85: =ABS(A85-W85) -> 66 | Y85: =VLOOKUP(M85,Hoja3!$L$2:$X$26,13,0) -> 42 | Z85: ACTIVO
A86: 45762 | D86: MARTES | E86: TU EMPRESA SEGURA | F86: LUZ | G86: LIANA OCAMPO | H86: Cédula de Ciudadanía | I86: 1036778480 | J86: Locampo@picados.com.co | K86: 3127198417 | L86: INVERSIONES VALLEJUELO S.A.S. | M86: 900655932 | N86: 45762 | O86: 0.40972222 | P86: 3 | Q86: =IF(OR(P86=1,P86=2,P86=3),106666,IF(OR(P86=4,P86=5),213000,"")) -> 106666 | R86: SI | S86: PLANEAR | T86: 1.0.6 Diagnóstico del Sistema de Gestión de Seguridad y Salud en el Trabajo (SG-SST) 0312 DE 2019 | U86: =IFERROR(VLOOKUP(T86,PHVA!$B$2:$C$74,2,0),0) -> 2 | V86: Pendiente firma de representante legal en responsabilidades del sistema de gestion y en termino y condiciones,pendiente enviar correo con documentos de rut y camara y comercio se realizo el diagnostico inicial. | W86: 45807 | X86: =ABS(A86-W86) -> 45 | Y86: =VLOOKUP(M86,Hoja3!$L$2:$X$26,13,0) -> 42 | Z86: ACTIVO
A87: 45769 | D87: MARTES | E87: TU EMPRESA SEGURA | F87: LUZ | G87: LIANA OCAMPO | H87: Cédula de Ciudadanía | I87: 1036778480 | J87: Locampo@picados.com.co | K87: 3127198417 | L87: INVERSIONES VALLEJUELO S.A.S. | M87: 900655932 | N87: 45769 | O87: 0.40972222 | P87: 3 | Q87: =IF(OR(P87=1,P87=2,P87=3),106666,IF(OR(P87=4,P87=5),213000,"")) -> 106666 | R87: SI | S87: PLANEAR | T87: 1.1.4 Afiliación al Sistema General de Riesgos Laborales | U87: =IFERROR(VLOOKUP(T87,PHVA!$B$2:$C$74,2,0),0) -> 0.5 | V87: el dia viernes 22 de abril Doña Liliana ocampo refiere manejar la plataforma y queda pendiente por su parte enviar correo electronico con rut,camara y comercio,logo,ARL.EPS Y adjuntar en el numeral 1.1.4 los certificados mes a mes de afiliaciones ,refiere tambien ya haber firmado terminos y condiciones . | W87: 45807 | X87: =ABS(A87-W87) -> 38 | Y87: =VLOOKUP(M87,Hoja3!$L$2:$X$26,13,0) -> 42 | Z87: ACTIVO
A88: 45776 | D88: MARTES | E88: TU EMPRESA SEGURA | F88: LUZ | G88: LIANA OCAMPO | H88: Cédula de Ciudadanía | I88: 1036778480 | J88: Locampo@picados.com.co | K88: 3127198417 | L88: INVERSIONES VALLEJUELO S.A.S. | M88: 900655932 | N88: 45776 | O88: 0.40972222 | P88: 3 | Q88: =IF(OR(P88=1,P88=2,P88=3),106666,IF(OR(P88=4,P88=5),213000,"")) -> 106666 | R88: NO | S88: PLANEAR | T88: 0. No conexión | U88: =IFERROR(VLOOKUP(T88,PHVA!$B$2:$C$74,2,0),0) -> 0 | V88: problemas con el interneth y conexion luz estrada ver correo del dia 30/4/2025 donde se informa el inconveniente con mi plataforma,no podia conectarme. | W88: 45807 | X88: =ABS(A88-W88) -> 31 | Y88: =VLOOKUP(M88,Hoja3!$L$2:$X$26,13,0) -> 42 | Z88: ACTIVO
A89: 45783 | D89: MARTES | E89: TU EMPRESA SEGURA | F89: LUZ | G89: LIANA OCAMPO | H89: Cédula de Ciudadanía | I89: 1036778480 | J89: Locampo@picados.com.co | K89: 3127198417 | L89: INVERSIONES VALLEJUELO S.A.S. | M89: 900655932 | N89: 45783 | O89: 0.40972222 | P89: 3 | Q89: =IF(OR(P89=1,P89=2,P89=3),106666,IF(OR(P89=4,P89=5),213000,"")) -> 106666 | R89: SI | S89: PLANEAR | T89: 1.1.1. Responsable del Sistema de Gestión de Seguridad y Salud en el Trabajo SG-SST | U89: =IFERROR(VLOOKUP(T89,PHVA!$B$2:$C$74,2,0),0) -> 0.5 | V89: se realiza diligenciamiento de documento de responsable,,se inicia con archivo documental y se deja tarea de diligenciamiento de perfilsociodemografico. | W89: 45807 | X89: =ABS(A89-W89) -> 24 | Y89: =VLOOKUP(M89,Hoja3!$L$2:$X$26,13,0) -> 42 | Z89: ACTIVO
A90: 45790 | D90: MARTES | E90: TU EMPRESA SEGURA | F90: LUZ | G90: LIANA OCAMPO | H90: Cédula de Ciudadanía | I90: 1036778480 | J90: Locampo@picados.com.co | K90: 3127198417 | L90: INVERSIONES VALLEJUELO S.A.S. | M90: 900655932 | N90: 45790 | O90: 0.40972222 | P90: 3 | Q90: =IF(OR(P90=1,P90=2,P90=3),106666,IF(OR(P90=4,P90=5),213000,"")) -> 106666 | R90: SI | S90: HACER | T90: 3.1.1 Descripcion sociodemografica.Diagnostico de Condiciones de Salud | U90: =IFERROR(VLOOKUP(T90,PHVA!$B$2:$C$74,2,0),0) -> 1 | V90: se continua diligenciando el archivo documental,pendiente perfilsociodemografico,no se adelanta mucho porque no era claro el tema de evidencias de perfil y de archivo documental.solicita correo de la grabacion de la conexion. | W90: 45807 | X90: =ABS(A90-W90) -> 17 | Y90: =VLOOKUP(M90,Hoja3!$L$2:$X$26,13,0) -> 42 | Z90: ACTIVO
A91: 45797 | D91: MARTES | E91: TU EMPRESA SEGURA | F91: LUZ | G91: LIANA OCAMPO | H91: Cédula de Ciudadanía | I91: 1036778480 | J91: Locampo@picados.com.co | K91: 3127198417 | L91: INVERSIONES VALLEJUELO S.A.S. | M91: 900655932 | N91: 45797 | O91: 0.40972222 | P91: 3 | Q91: =IF(OR(P91=1,P91=2,P91=3),106666,IF(OR(P91=4,P91=5),213000,"")) -> 106666 | R91: SI | S91: PLANEAR | T91: 2.5.1 Archivo o retención documental del Sistema de Gestión en Seguridad y Salud en el Trabajo SG-SST | U91: =IFERROR(VLOOKUP(T91,PHVA!$B$2:$C$74,2,0),0) -> 2 | V91: Solicita que se le revise todo el numeral 2.5.1 cree que repitio datos,solicita paso a paso de subir firmas y enviar correo del numeral 1.1.4 para subir evidencias. | W91: 45807 | X91: =ABS(A91-W91) -> 10 | Y91: =VLOOKUP(M91,Hoja3!$L$2:$X$26,13,0) -> 42 | Z91: ACTIVO
D92: MARTES | E92: TU EMPRESA SEGURA | F92: LUZ | G92: LIANA OCAMPO | H92: Cédula de Ciudadanía | I92: 1036778480 | J92: Locampo@picados.com.co | K92: 3127198417 | L92: INVERSIONES VALLEJUELO S.A.S. | M92: 900655932 | N92: 45777 | P92: 3 | Q92: =IF(OR(P92=1,P92=2,P92=3),106666,IF(OR(P92=4,P92=5),213000,"")) -> 106666 | R92: SI | S92: PLANEAR | T92: 1.0.4 Acompañamiiento/Asesoría sobre SGSST | U92: =IFERROR(VLOOKUP(T92,PHVA!$B$2:$C$74,2,0),0) -> 2 | V92: Solicita que se le revise todo el numeral 2.5.1 cree que repitio datos,solicita paso a paso de subir firmas y enviar correo del numeral 1.1.4 para subir evidencias. | W92: 45807 | X92: =ABS(A92-W92) -> 45807 | Y92: =VLOOKUP(M92,Hoja3!$L$2:$X$26,13,0) -> 42 | Z92: ACTIVO
A93: 45804 | D93: MARTES | E93: TU EMPRESA SEGURA | F93: LUZ | G93: LIANA OCAMPO | H93: Cédula de Ciudadanía | I93: 1036778480 | J93: Locampo@picados.com.co | K93: 3127198417 | L93: INVERSIONES VALLEJUELO S.A.S. | M93: 900655932 | N93: 45804 | O93: 0.40972222 | P93: 3 | Q93: =IF(OR(P93=1,P93=2,P93=3),106666,IF(OR(P93=4,P93=5),213000,"")) -> 106666 | R93: SI | S93: PLANEAR | T93: 1.0.6 Diagnóstico del Sistema de Gestión de Seguridad y Salud en el Trabajo (SG-SST) 0312 DE 2019 | U93: =IFERROR(VLOOKUP(T93,PHVA!$B$2:$C$74,2,0),0) -> 2 | V93: Se realiza evalucion inicial y se revisa numeral 1.1.4 (Aceptable) | W93: 45807 | X93: =ABS(A93-W93) -> 3 | Y93: =VLOOKUP(M93,Hoja3!$L$2:$X$26,13,0) -> 42 | Z93: ACTIVO
F94: LUZ | G94: Jorge Eliecer Gómez Garcia | H94: Cédula de Ciudadanía | I94: 1128403927 | J94: gerenciacakareos@gmail.com | K94: 3148312199 | L94: JORGE ELIECER GOMEZ | M94: 1128403927 | N94: 45811 | O94: 0.62847222 | P94: 1 | Q94: =IF(OR(P94=1,P94=2,P94=3),106666,IF(OR(P94=4,P94=5),213000,"")) -> 106666 | R94: SI | S94: PLANEAR | T94: 0. No conexión | U94: =IFERROR(VLOOKUP(T94,PHVA!$B$2:$C$74,2,0),0) -> 0 | V94: Esta en duda si continua con tu empresa segura comfama o sigue con las niñas que le llevan el sistema en el momento. | W94: 45807 | X94: =ABS(A94-W94) -> 45807 | Y94: =VLOOKUP(M94,Hoja3!$L$2:$X$26,13,0) -> 5 | Z94: ACTIVO
A95: 45804 | D95: MARTES | E95: TU EMPRESA SEGURA | F95: LUZ | G95: Jorge Eliecer Gómez Garcia | H95: Cédula de Ciudadanía | I95: 1128403927 | J95: gerenciacakareos@gmail.com | K95: 3017402779 | L95: JORGE ELIECER GOMEZ | M95: 1128403927 | N95: 45804 | O95: 0.62847222 | P95: 1 | Q95: =IF(OR(P95=1,P95=2,P95=3),106666,IF(OR(P95=4,P95=5),213000,"")) -> 106666 | R95: CONEXIÓN AUTÓNOMA DE ANALISTA | S95: PLANEAR | T95: 0. No conexión | U95: =IFERROR(VLOOKUP(T95,PHVA!$B$2:$C$74,2,0),0) -> 0 | V95: Refiere que espero todo el dia la conexion ,pero hay evidencias que no contesto el celular en llamada ,ni mensaje de whatsapp.en la grabacion de la misma fecha d econexion. | W95: 45807 | X95: =ABS(A95-W95) -> 3 | Y95: =VLOOKUP(M95,Hoja3!$L$2:$X$26,13,0) -> 5 | Z95: ACTIVO
A96: 45741 | B96: MARZO | C96: 3 | D96: MARTES | E96: TU EMPRESA SEGURA | F96: JUAN DIEGO | G96: LADY NATALIA RODRÍGUEZ OSPINA | H96: Cédula de Ciudadanía | I96: 1036937209 | J96: Natalia.rodriguez7209@gmail.com | K96: 3128650034 | L96: JULIAN GALLEGO CASTRO | M96: 15448886 | N96: 45741 | O96: 1:00p.m. | P96: 1 | Q96: =IF(OR(P96=1,P96=2,P96=3),106666,IF(OR(P96=4,P96=5),213000,"")) -> 106666 | R96: SI | S96: PLANEAR | T96: 1.0.0 Bienvenida | U96: =IFERROR(VLOOKUP(T96,PHVA!$B$2:$C$74,2,0),0) -> 1 | V96: el dia viernes 21 de marzo se llamo a la empresa para validar la llegada del correo electronico con el usuario y la contraseña a lo cual indicaron que si les llego y que no han tenido ningun inconveniente. Primer conexión explicación del proyecto | W96: 45807 | X96: =ABS(A96-W96) -> 66 | Y96: =VLOOKUP(M96,Hoja3!$L$2:$X$26,13,0) -> 11 | Z96: ACTIVO
A97: 45752 | D97: SABADO | E97: TU EMPRESA SEGURA | F97: JUAN DIEGO | G97: LADY NATALIA RODRÍGUEZ OSPINA | H97: Cédula de Ciudadanía | I97: 1036937209 | J97: Natalia.rodriguez7209@gmail.com | K97: 3128650034 | L97: JULIAN GALLEGO CASTRO | M97: 15448886 | N97: 45752 | O97: 1:00p.m. | P97: 1 | Q97: =IF(OR(P97=1,P97=2,P97=3),106666,IF(OR(P97=4,P97=5),213000,"")) -> 106666 | R97: SI | S97: PLANEAR | T97: 1.0.1 Firma de Términos y Condiciones | U97: =IFERROR(VLOOKUP(T97,PHVA!$B$2:$C$74,2,0),0) -> 1 | V97: Segunda conexión validación de usuario y contraseña, firma de de Términos y Condiciones | W97: 45807 | X97: =ABS(A97-W97) -> 55 | Y97: =VLOOKUP(M97,Hoja3!$L$2:$X$26,13,0) -> 11 | Z97: ACTIVO
A98: 45759 | D98: SABADO | E98: TU EMPRESA SEGURA | F98: JUAN DIEGO | G98: LADY NATALIA RODRÍGUEZ OSPINA | H98: Cédula de Ciudadanía | I98: 1036937209 | J98: Natalia.rodriguez7209@gmail.com | K98: 3128650034 | L98: JULIAN GALLEGO CASTRO | M98: 15448886 | N98: 45759 | O98: 8:05AM | P98: 1 | Q98: =IF(OR(P98=1,P98=2,P98=3),106666,IF(OR(P98=4,P98=5),213000,"")) -> 106666 | R98: SI | S98: PLANEAR | T98: 1.0.5 Diagnóstico de Madurez | U98: =IFERROR(VLOOKUP(T98,PHVA!$B$2:$C$74,2,0),0) -> 3 | V98: Se realiza diagnóstico de madurez, con resultado aprobado y se adelanta términos y condiciones y se inicia perfil sociodemográfico, y se envía estándar de seguridad de cuchillo para la cocina. | W98: 45807 | X98: =ABS(A98-W98) -> 48 | Y98: =VLOOKUP(M98,Hoja3!$L$2:$X$26,13,0) -> 11 | Z98: ACTIVO
A99: 45766 | D99: SABADO | E99: TU EMPRESA SEGURA | F99: JUAN DIEGO | G99: LADY NATALIA RODRÍGUEZ OSPINA | H99: Cédula de Ciudadanía | I99: 1036937209 | J99: Natalia.rodriguez7209@gmail.com | K99: 3128650034 | L99: JULIAN GALLEGO CASTRO | M99: 15448886 | N99: 45766 | O99: 8:05AM | P99: 1 | Q99: =IF(OR(P99=1,P99=2,P99=3),106666,IF(OR(P99=4,P99=5),213000,"")) -> 106666 | R99: SI | S99: PLANEAR | T99: 1.0.6 Diagnóstico del Sistema de Gestión de Seguridad y Salud en el Trabajo (SG-SST) 0312 DE 2019 | U99: =IFERROR(VLOOKUP(T99,PHVA!$B$2:$C$74,2,0),0) -> 2 | V99: se inicia a las8:am, se consulta sobre novedades de ausentismos por vacaciones y no se reportan, se consulta sobre novedades de acceso a plataforma y no se reportan novedades negativas, se inicia con la carga de examenes médicos en el modulo de salud laboral y de apgo de seguridad social en pago al sgrl, se continua con la evaluacion inicial para ir generando el puntaje segun los requerimientos de la Res. 0312 del 2019, terminamos a las 9am | W99: 45807 | X99: =ABS(A99-W99) -> 41 | Y99: =VLOOKUP(M99,Hoja3!$L$2:$X$26,13,0) -> 11 | Z99: ACTIVO
A100: 45787 | D100: SABADO | E100: TU EMPRESA SEGURA | F100: JUAN DIEGO | G100: LADY NATALIA RODRÍGUEZ OSPINA | H100: Cédula de Ciudadanía | I100: 1036937209 | J100: Natalia.rodriguez7209@gmail.com | K100: 3128650034 | L100: JULIAN GALLEGO CASTRO | M100: 15448886 | N100: 45787 | O100: 8:05AM | P100: 1 | Q100: =IF(OR(P100=1,P100=2,P100=3),106666,IF(OR(P100=4,P100=5),213000,"")) -> 106666 | R100: SI | S100: PLANEAR | T100: 1.1.3 Asignación de recursos para el Sistema de Gestión en Seguridad y Salud en el Trabajo – SG-SST | U100: =IFERROR(VLOOKUP(T100,PHVA!$B$2:$C$74,2,0),0) -> 0.5 | V100: S e ingresa incapacidad a regi. de ausentismos en plataforma, tambien,se diligenca el indicador de enfermedd general; se avanza en la matriz de asignacion de recursos; y se envia el MEDEVAC | W100: 45807 | X100: =ABS(A100-W100) -> 20 | Y100: =VLOOKUP(M100,Hoja3!$L$2:$X$26,13,0) -> 11 | Z100: ACTIVO
...

Sheet Hoja3
A1: FECHA INICIO DEL PROGRAMA | B1: MES DE INICIO COBERTURA | C1: Día | D1: Programa | E1: Analista | F1: Nombre | G1: Tipo de documento | H1: N.Identificación | I1: Correo electrónico1 | J1: Número de celular | K1: Nombre de la empresa | L1: NIT | M1: Conexión | N1: Hora | O1: HUBO CONEXIÓN | P1: NIVEL DE RIESGO | Q1: VALOR | R1: CICLO | S1: ESTANDAR 0312 DE 2019 | T1: PORCENTAJE | U1: Acompañamiento 1 | V1: FECHA DE INFORME | W1: DÍAS EN EL PROGRAMA | X1: NÚMERO DE EMPLEADOS | Y1: ACTIVO/INACTIVO
A2: 45797 | C2: MARTES | D2: TU EMPRESA SEGURA | E2: LUZ | F2: ALEXIS PÉREZ GÓMEZ | G2: Cédula de Ciudadanía | H2: 1040325965 | I2: contacto@villaclara.com.co | J2: 3132973915 | K2: AGROINSUMOS VILLACLARA SAS | L2: 901250630 | M2: 45797 | N2: 11:30 a.m | O2: si | P2: 1 | Q2: 106.666 | R2: PLANEAR | S2: 1.0.6 Diagnóstico del Sistema de Gestión de Seguridad y Salud en el Trabajo (SG-SST) 0312 DE 2019 | T2: 2 | U2: No firmo firma de termminos y condiciones por temas de no tener contraseña y usuario,se le presenta el programa .se le realiza evaluacion inicial | V2: 45807 | W2: 10 | X2: 14 | Y2: ACTIVO
A3: 45751 | C3: VIERNES | D3: TU EMPRESA SEGURA | E3: Juan Diego | F3: MERCEDES CARVAJAL OSPINA | G3: Cédula de Ciudadanía | H3: 21481666 | I3: mercedesemprendedora2023@gmail.com | J3: 3053436587 | K3: ALMA BOTANICA SAS | L3: 901817841 | M3: 45751 | N3: 11:30a.m | O3: si | P3: 4 | Q3: 213000 | R3: PLANEAR | S3: 1.0.4 Acompañamiiento/Asesoría sobre SGSST | T3: 2 | U3: el dia martes 1 de abril se llamo a la empresa para poder validar si se peude contactar ya que s ehabia intentado anteriormente y no se habia logrado Presentación del Programa: Registro Usuario y contraseña, términos y condiciones y se explica reporte de incidentes y accidentes ante la ARL | V3: 45807 | W3: 56 | X3: 2 | Y3: ACTIVO
A4: 45744 | C4: VIERNES | D4: TU EMPRESA SEGURA | E4: Cristhian | F4: Ana Maria Campuzano Arboleda | G4: Cédula de Ciudadanía | H4: 1007445947 | I4: anam_campuzano@hotmail.com | J4: 3217213077 | K4: ANA CAMPUZANO ARBOLEDA | L4: 1007445947 | M4: 45744 | N4: 11:30a.m | O4: si | P4: 2 | Q4: 106.666 | R4: PLANEAR | S4: 1.0.0 Bienvenida | T4: 1 | U4: Bienvenida al programa, se le explica detalladamente en que consiste y la duración estimada, se Indica cómo firmar los términos y condiciones, se agenda la reunión periódica, semanal, los viernes de 11:30 a 12:15pm | V4: 45807 | W4: 63 | X4: 2 | Y4: ACTIVO
A5: 45751 | C5: VIERNES | D5: TU EMPRESA SEGURA | E5: Juan Diego | F5: MELISSA MARIA ROMAN BURITICA | G5: Cédula de Ciudadanía | H5: 1040039119 | I5: gestionhumana@blackriverflowers.com | J5: 3173882936 | K5: BLACKRIVER FLOWERS SAS C I | L5: 900841005 | M5: 45751 | N5: 10:40a. m. | O5: si | P5: 3 | Q5: 106.666 | R5: PLANEAR | S5: 1.0.1 Firma de Términos y Condiciones | T5: 1 | U5: el dia viernes 21 de marzo se llamo a la empresa para validar la llegada del correo electronico con el usuario y la contraseña a lo cual indicaron que si les llego y que no han tenido ningun inconveniente | V5: 45807 | W5: 56 | X5: 55 | Y5: ACTIVO
A6: 45751 | C6: VIERNES | D6: TU EMPRESA SEGURA | E6: Juan Diego | F6: CLAUDIA PATRICIA MOLINA SANTOS | G6: Cédula de Ciudadanía | H6: 1070989191 | I6: clau300625@hotmail.es | J6: 3132973915 | K6: BORJA FLOWERS SAS | L6: 901546567 | M6: 45751 | N6: 3:55p. m. | O6: si | P6: 3 | Q6: 106.666 | R6: PLANEAR | S6: 1.0.0 Bienvenida | T6: 1 | U6: el dia viernes 21 de marzo se llamo a la empresa para validar la llegada del correo electronico con el usuario y la contraseña a lo cual indicaron que si les llego y que no han tenido ningun inconveniente | V6: 45807 | W6: 56 | X6: 30 | Y6: ACTIVO
A7: 45717 | C7: JUEVES | D7: TU EMPRESA SEGURA | E7: LUZ | F7: JUBER NEVARDO MARTINEZ GIRALDO | G7: Cédula de Ciudadanía | H7: 1039685226 | I7: adm.car.mc@gmail.com | J7: 3206709930 | K7: CARNES MONTECARLO | L7: 43476587 | M7: 45792 | N7: 1:15 p.m | O7: no | P7: 3 | Q7: 106.666 | R7: PLANEAR | S7: 1.0.2 Socialización SGSST | T7: 2 | U7: Solicita reprogramar reunion para otro dia,teniendo en cuenta que la agenda esta copada ,se le enviara por correo tareas para la proxima conexion. | V7: 45807 | W7: 90 | X7: 4 | Y7: ACTIVO
A8: 45751 | C8: VIERNES | D8: TU EMPRESA SEGURA | E8: Juan Diego | F8: MONICA YANETH OCAMPO SERNA | G8: Cédula de Ciudadanía | H8: 1036780830 | I8: floresmundocolores@gmail.com | J8: 3147830285 | K8: CI FLORES MUNDO COLORES SAS | L8: 900509996 | M8: 45751 | N8: 3:05PM | O8: si | P8: 3 | Q8: 106.666 | R8: PLANEAR | S8: 1.0.0 Bienvenida | T8: 1 | U8: el dia viernes 21 de marzo se llamo a la empresa para validar la llegada del correo electronico con el usuario y la contraseña a lo cual indicaron que si les llego y que no han tenido ningun inconveniente | V8: 45807 | W8: 56 | X8: 3 | Y8: ACTIVO
A9: 45751 | C9: VIERNES | D9: TU EMPRESA SEGURA | E9: Cristhian | F9: Jorge ignacio Martínez García | G9: Cédula de Ciudadanía | H9: 70952794 | I9: j73jimg@hotmail.com | J9: 3216422617 | K9: EMTURPE LIMITADA | L9: 900112921 | M9: 45751 | N9: 7:15a. m. | O9: si | P9: 4 | Q9: 213000 | R9: PLANEAR | S9: 1.0.0 Bienvenida | T9: 1 | U9: se realiza la reunion de bienvenida pero en la mitad de la reunion se tuvieron problemas de connexion por lo cual se finaliza la misma | V9: 45807 | W9: 56 | X9: 5 | Y9: ACTIVO
A10: 45797 | C10: MARTES | D10: TU EMPRESA SEGURA | E10: LUZ | J10: 3104997696 | K10: ESTRUCTURAS METALICAS DEL CHOCO | M10: 45797 | N10: 10:40 a.m | O10: si | P10: 3 | Q10: 106.666 | R10: PLANEAR | S10: 1.0.0 Bienvenida | T10: 1 | U10: Bienvenida al programa, No firmo firma de termminos y condiciones por temas de no tener contraseña y usuario,se le presenta el programa .se le realiza evaluacion inicial | V10: 45807 | W10: 10 | X10: 4 | Y10: ACTIVO
A11: 45797 | C11: MARTES | D11: TU EMPRESA SEGURA | E11: LUZ | F11: Kerly Andrea Ortiz Ramirez | G11: Cédula de Ciudadanía | H11: 1128395305 | I11: Kerlyandreaortiz1407@gmail.com | J11: 3128926799 | K11: FOTO SCANNER | L11: 1128395305 | M11: 45797 | N11: 1:00 p.m | O11: si | P11: 1 | Q11: 106.666 | R11: PLANEAR | S11: 1.0.0 Bienvenida | T11: 1 | U11: Se realiza bienvenida, no firmo firma de termminos y condiciones por temas de no tener contraseña y usuario,se le presenta el programa . | V11: 45807 | W11: 10 | X11: 3 | Y11: ACTIVO
A12: 45775 | C12: VIERNES | D12: TU EMPRESA SEGURA | E12: Cristhian | F12: LUISA GARCIA | G12: Cédula de Ciudadanía | H12: 1036929374 | I12: luisayepes02@gmail.com | J12: 3194892497 | K12: HYDRANFLOWERS S.A.S | L12: 901166099 | M12: 46133 | N12: 11:00a. m. | O12: si | P12: 2 | Q12: 106.666 | R12: PLANEAR | S12: 1.0.0 Bienvenida | T12: 1 | U12: Bienvenida al programa, se le explica detalladamente en que consiste y la duración estimada, se Indica cómo firmar los términos y condiciones, se agenda la reunión periódica, semanal, los viernes de 3:00 a 3:45pm, se actualiza el correo de contacto: claoarbo@hotmail.com | V12: 45807 | W12: 32 | X12: 7 | Y12: ACTIVO
A13: 45741 | C13: MARTES | D13: TU EMPRESA SEGURA | E13: LUZ | F13: LIANA OCAMPO | G13: Cédula de Ciudadanía | H13: 1036778480 | I13: Locampo@picados.com.co | J13: 3127198417 | K13: INVERSIONES VALLEJUELO S.A.S. | L13: 900655932 | M13: 45741 | N13: 11:00 AM - 12:00 PM | O13: si | P13: 3 | Q13: 106.666 | R13: PLANEAR | S13: 1.0.0 Bienvenida | T13: 1 | U13: el dia viernes 21 de marzo se llamo a la empresa para validar la llegada del correo electronico con el usuario y la contraseña a lo cual indicaron que si les llego y que no han tenido ningun inconveniente | V13: 45807 | W13: 66 | X13: 42 | Y13: ACTIVO
A14: 45811 | E14: LUZ | F14: Jorge Eliecer Gómez Garcia | G14: Cédula de Ciudadanía | H14: 1128403927 | I14: gerenciacakareos@gmail.com | J14: 3148312199 | K14: JORGE ELIECER GOMEZ | L14: 1128403927 | M14: 45811 | N14: 0.62847222 | O14: si | P14: 1 | Q14: 106.666 | R14: PLANEAR | S14: 0. No conexión | T14: 0 | U14: Esta en duda si continua con tu empresa segura comfama o sigue con las niñas que le llevan el sistema en el momento. | V14: 45807 | W14: 4 | X14: 5 | Y14: ACTIVO
A15: 45741 | C15: MARTES | D15: TU EMPRESA SEGURA | E15: JUAN DIEGO | F15: LADY NATALIA RODRÍGUEZ OSPINA | G15: Cédula de Ciudadanía | H15: 1036937209 | I15: Natalia.rodriguez7209@gmail.com | J15: 3128650034 | K15: JULIAN GALLEGO CASTRO | L15: 15448886 | M15: 45741 | N15: 1:00p.m. | O15: si | P15: 1 | Q15: 106.666 | R15: PLANEAR | S15: 1.0.0 Bienvenida | T15: 1 | U15: el dia viernes 21 de marzo se llamo a la empresa para validar la llegada del correo electronico con el usuario y la contraseña a lo cual indicaron que si les llego y que no han tenido ningun inconveniente. Primer conexión explicación del proyecto | V15: 45807 | W15: 66 | X15: 11 | Y15: ACTIVO
A16: 45744 | C16: VIERNES | D16: TU EMPRESA SEGURA | E16: Cristhian | F16: Dora Luz Arbelaez | G16: Cédula de Ciudadanía | H16: 39382394 | I16: doraluzarbelaez@gmail.com | J16: 3113247283 | K16: LACTEOS BUENA VISTA SABORES NATURALES S A | L16: 900167311 | M16: 46133 | N16: 1:40PM | O16: si | P16: 3 | Q16: 106.666 | R16: PLANEAR | S16: 1.0.0 Bienvenida | T16: 1 | U16: Bienvenida al programa, se le explica detalladamente en que consiste y la duración estimada, se Indica cómo firmar los términos y condiciones, se agenda la reunión periódica, semanal, los viernes de 1:30 a 2:15Pm | V16: 45807 | W16: 63 | X16: 11 | Y16: ACTIVO
A17: 45737 | C17: VIERNES | D17: TU EMPRESA SEGURA | E17: Cristhian | F17: JUAN FELIPE LÓPEZ OROZCO | G17: Cédula de Ciudadanía | H17: 15356506 | I17: felipelopezorozco2020@gmail.com ,lopetransvolq@gmail.com | J17: 3136468404 | K17: LOPETRANS SAS | L17: 901636833 | M17: 45737 | N17: 7:00AM | O17: si | P17: 1 | Q17: 106.666 | R17: PLANEAR | S17: 1.0.0 Bienvenida | T17: 1 | U17: Bienvenida al programa, se le explica detalladamente en que consiste y la duración estimada, se Indica cómo firmar los términos y condiciones, se agenda la reunión periódica, semanal, los Lunes de 7:15 a 8:00am | V17: 45807 | W17: 70 | X17: 5 | Y17: ACTIVO
A18: 45735 | C18: MERCOLES | D18: TU EMPRESA SEGURA | E18: CRISTIAN | F18: BRANDON YESID VELASQUEZ LOPEZ | G18: Cédula de Ciudadanía | H18: 1013654370 | I18: Maderas.sanrafael@hotmail.com | J18: 3105299313 | K18: MADERAS SAN RAFAEL | L18: 1013654370 | M18: 45735 | N18: 02:00p. m. | O18: si | P18: 4 | Q18: 213000 | R18: PLANEAR | S18: 1.0.0 Bienvenida | T18: 1 | U18: Bienvenida al programa, se le explica detalladamente en que consiste y la duración estimada, se Indica cómo firmar los términos y condiciones, se agenda la reunión periódica, semanal | V18: 45807 | W18: 72 | X18: 4 | Y18: ACTIVO
A19: 45717 | C19: JUEVES | D19: TU EMPRESA SEGURA | E19: LUZ | F19: OLGA LUCIA LOPEZ ALVAREZ | G19: Cédula de Ciudadanía | H19: 43862379 | I19: Asesorias@encontac.com | J19: 3147571005 | K19: OLGA LÓPEZ | L19: 43862379 | M19: 45785 | O19: si | P19: 1 | Q19: 106.666 | R19: PLANEAR | S19: 1.1.1. Responsable del Sistema de Gestión de Seguridad y Salud en el Trabajo SG-SST | T19: 0,5 | U19: se realiza digitacion y explicacion de archivo,se le explica el perfilsociodemografica y queda como tarea,se revisa afiliaciones y documento de responsable del sistema. | V19: 45807 | W19: 90 | X19: 2 | Y19: ACTIVO
A20: 45751 | C20: VIERNES | D20: TU EMPRESA SEGURA | E20: Juan Diego | F20: CARLOS ALBERTO BEJARANO CAMACHO | G20: Cédula de Ciudadanía | H20: 79291337 | I20: carlos.bejarano@prosolar.com.co | J20: 3104387811 | K20: PROSOLAR S.A.S | L20: 901039724 | M20: 45751 | N20: 9:00a. m. | O20: si | P20: 2 | Q20: 106.666 | R20: PLANEAR | S20: 1.0.0 Bienvenida | T20: 1 | U20: el dia viernes 21 de marzo se llamo a la empresa para validar la llegada del correo electronico con el usuario y la contraseña a lo cual indicaron que si les llego y que no han tenido ningun inconveniente | V20: 45807 | W20: 56 | X20: 6 | Y20: ACTIVO
A21: 45733 | C21: LUNES | D21: TU EMPRESA SEGURA | E21: Cristhian | F21: SAUL GÓMEZ JARAMILLO | G21: Cédula de Ciudadanía | H21: 15384344 | I21: saul.gomez@hotmai.es | J21: 3148500297 | K21: SAÚL GÓMEZ | L21: 15384344 | M21: 45733 | N21: 02:00p. m. | O21: si | P21: 2 | Q21: 106.666 | R21: PLANEAR | S21: 1.0.0 Bienvenida | T21: 1 | V21: 45807 | W21: 74 | X21: 8 | Y21: ACTIVO
A22: 45724 | C22: JUEVES | D22: TU EMPRESA SEGURA | E22: LUZ | F22: MANDIRELIS FLOREZ MARIN | G22: Cédula de Ciudadanía | H22: 39453906 | I22: mandy.f.m@hotmail.com | J22: 3128523870 | K22: SUMINISTRO Y TRANSPORTE DE MATERIAL RIOS Y FLOREZ SAS | L22: 901590411 | M22: 45776 | N22: 9:00a, m. | O22: si | P22: 2 | Q22: 106.666 | R22: PLANEAR | S22: 1.0.1 Firma de Términos y Condiciones | T22: 1 | U22: Se actualiza perfilsociodemografico,firma de terminos y condiciones,presentacion del programa. | V22: 45807 | W22: 83 | X22: 23 | Y22: ACTIVO
A23: 45731 | C23: JUEVES | D23: TU EMPRESA SEGURA | E23: LUZ | F23: JAVIER IGNACIO GARCIA GARCIA | G23: Cédula de Ciudadanía | H23: 15380272 | I23: teccons@hotmail.com | J23: 3113177651 | K23: TECCONS S.A.S | L23: 900709843 | M23: 45792 | N23: 3:55p. m. | O23: si | P23: 5 | Q23: 213000 | R23: PLANEAR | S23: 1.1.4 Afiliación al Sistema General de Riesgos Laborales | T23: 0,5 | U23: Se realiza el perfilsociodemografico,se le enviara correo de verificacion para montar el numeral 1.1.4. | V23: 45807 | W23: 76 | X23: 2 | Y23: ACTIVO
A24: 45717 | C24: JUEVES | D24: TU EMPRESA SEGURA | E24: LUZ | F24: YURANI ANDREA MADRID MORALES | G24: Cédula de Ciudadanía | H24: 1039681747 | I24: Yurandra198720@gmail.com | J24: 3136884875 | K24: TROPICAL1987 | L24: 1039681747 | M24: 45785 | N24: 7:15 a.m | O24: si | P24: 3 | Q24: 106.666 | R24: PLANEAR | S24: 1.1.1. Responsable del Sistema de Gestión de Seguridad y Salud en el Trabajo SG-SST | T24: 0,5 | U24: Se diligencia responsabilidades,se adelanta tema de archivo documental,se envia correo de como montar evidencia de afiliacion,como realizar el perfilsociodemografico. | V24: 45807 | W24: 90 | X24: 4 | Y24: ACTIVO
A25: 45742 | C25: MIERCOLES | D25: TU EMPRESA SEGURA | E25: Cristhian | F25: SANDRA MILENA ARANGO JARAMILLO | G25: Cédula de Ciudadanía | H25: 39189386 | I25: sandra.arango@urantus.com | J25: 3022152280 | K25: URANTUS GREENHOUSES S.A.S | L25: 901268585 | M25: 45742 | N25: 9:00AM | O25: si | P25: 5 | Q25: 213000 | R25: PLANEAR | S25: 1.0.0 Bienvenida | T25: 1 | U25: Bienvenida al programa, se le explica detalladamente en que consiste y la duración estimada, se Indica cómo firmar los términos y condiciones, se agenda la reunión periódica, semanal, los viernes de 10:40 a 11:25Am | V25: 45807 | W25: 65 | X25: 9 | Y25: ACTIVO
A26: 45751 | C26: VIERNES | D26: TU EMPRESA SEGURA | E26: Cristhian | F26: VANESSA VARGAS ALZATE | G26: Cédula de Ciudadanía | H26: 1037649854 | I26: avelicafe@gmail.com | J26: 3114323737 | K26: VANESSA VARGAS ALZATE | L26: 1037649854 | M26: 45751 | N26: 8:05a. m. | O26: si | P26: 2 | Q26: 106.666 | R26: PLANEAR | S26: 1.0.0 Bienvenida | T26: 1 | U26: el dia viernes 21 de marzo se llamo a la empresa para validar la llegada del correo electronico con el usuario y la contraseña a lo cual indicaron que si les llego y que no han tenido ningun inconveniente | V26: 45807 | W26: 56 | X26: 2 | Y26: ACTIVO

Sheet PHVA
A1: Ciclo PHVA | B1: ÍTEM ESTÁNDAR | C1: PORCENTAJE DE AVANCE | D1: MESES DE ACOMPAÑAMIENTO | E1: %POR MES | F1: ACTIVIDADES PLANEADAS | G1: ACTIVIDADES EJECUTADAS | H1: INDICADORES
A2: PLANEAR | B2: 1.0.0 Bienvenida | C2: 1 | D2: MES 1 | E2: =SUM(C2+C6+C7+C11+C10) -> 9 | F2: 5 | H2: =(F2*G2)/100 -> 0
A3: PLANEAR | B3: 0. No conexión | C3: 0 | D3: MES 1
A4: PLANEAR | B4: 0. No conexión Savanna | C4: 0 | D4: MES 1
A5: PLANEAR | B5: 0.1 Trabajo autónomo analista en plataforma | C5: 0.5 | D5: MES 1
A6: PLANEAR | B6: 1.0.1 Firma de Términos y Condiciones | C6: 1 | D6: MES 1
A7: PLANEAR | B7: 1.0.2 Socialización SGSST | C7: 2 | D7: MES 1
A8: PLANEAR | B8: 1.0.3 Navegando en la plataforma y beneficios del programa | C8: 1 | D8: MES 1
A9: PLANEAR | B9: 1.0.4 Acompañamiiento/Asesoría sobre SGSST | C9: 2 | D9: MES 1
A10: PLANEAR | B10: 1.0.5 Diagnóstico de Madurez | C10: 3 | D10: MES 1
A11: PLANEAR | B11: 1.0.6 Diagnóstico del Sistema de Gestión de Seguridad y Salud en el Trabajo (SG-SST) 0312 DE 2019 | C11: 2 | D11: MES 1 | F11: 5
A12: PLANEAR | B12: 1.0.8 Acompañamiento AT/EL | C12: 3 | D12: MES 2 | E12: =SUM(C12+C14+C15+C16) -> 8
A13: PLANEAR | B13: 1.0.8 Savanna Campañas de Sencibilización | C13: 4 | D13: MES 2
A14: PLANEAR | B14: 1.0.9 Savanna Ruta de Bienestar | C14: 4 | D14: MES 2
A15: PLANEAR | B15: 1.1.1. Responsable del Sistema de Gestión de Seguridad y Salud en el Trabajo SG-SST | C15: 0.5 | D15: MES 2
A16: PLANEAR | B16: 1.1.2 Responsabilidades en el Sistema de Gestión de Seguridad y Salud en el Trabajo – SG-SST | C16: 0.5 | D16: MES 2
A17: PLANEAR | B17: 1.1.3 Asignación de recursos para el Sistema de Gestión en Seguridad y Salud en el Trabajo – SG-SST | C17: 0.5 | D17: MES 3 | E17: =SUM(C17:C20) -> 2 | F17: 4
A18: PLANEAR | B18: 1.1.4 Afiliación al Sistema General de Riesgos Laborales | C18: 0.5 | D18: MES 3
A19: PLANEAR | B19: 1.1.5 Identificacion de trabajadores de alto riesgo y cotizacion de pension especial | C19: 0.5 | D19: MES 3
A20: PLANEAR | B20: 1.1.6 Conformación COPASST | C20: 0.5 | D20: MES 3
A21: PLANEAR | B21: 1.1.7 Capacitación COPASST | C21: 0.5 | D21: MES 4 | E21: =SUM(C21:C24) -> 5 | F21: 4
A22: PLANEAR | B22: 1.1.8 Conformación Comité de Convivencia | C22: 0.5 | D22: MES 4
A23: PLANEAR | B23: 1.2.1 Programa Capacitación promoción y prevención PYP | C23: 2 | D23: MES 4
A24: PLANEAR | B24: 1.2.2 Inducción y Reinducción en Sistema de Gestión de Seguridad y Salud en el Trabajo SG-SST, actividades de Promoción y Prevención PyP | C24: 2 | D24: MES 4
A25: PLANEAR | B25: 1.2.3 Responsables del Sistema de Gestión de Seguridad y Salud en el Trabajo SG-SST con curso virtual de 50 horas | C25: 2 | D25: MES 5 | E25: =SUM(C25:C28) -> 5 | F25: 4
A26: PLANEAR | B26: 2.1.1 Política del Sistema de Gestión de Seguridad y Salud en el Trabajo SG-SST firmada, fechada y comunicada al COPASST | C26: 1 | D26: MES 5
A27: PLANEAR | B27: 2.2.1 Objetivos definidos, claros, medibles, cuantificables, con metas, documentados, revisados del SG-SST | C27: 1 | D27: MES 5
A28: PLANEAR | B28: 2.3.1 Evaluación e identificación de prioridades | C28: 1 | D28: MES 5
A29: PLANEAR | B29: 2.4.1 Plan que identifica objetivos, metas, responsabilidad, recursos con cronograma y firmado | C29: 2 | D29: MES 6 | E29: =SUM(C29:C32) -> 7 | F29: 4
A30: PLANEAR | B30: 2.5.1 Archivo o retención documental del Sistema de Gestión en Seguridad y Salud en el Trabajo SG-SST | C30: 2 | D30: MES 6
A31: PLANEAR | B31: 2.6.1 Rendición sobre el desempeño | C31: 1 | D31: MES 6
A32: PLANEAR | B32: 2.7.1 Matriz legal | C32: 2 | D32: MES 6
A33: PLANEAR | B33: 2.8.1 Mecanismos de comunicación, auto reporte en Sistema de Gestión de Seguridad y Salud en el Trabajo SG-SST | C33: 1 | D33: MES 7 | E33: =SUM(C33:C36) -> 5 | F33: 4
A34: PLANEAR | B34: 2.9.1 Identificación, evaluación, para adquisición de productos y servicios en Sistema de Gestión de Seguridad y Salud en el Trabajo SG-SST | C34: 1 | D34: MES 7
A35: PLANEAR | B35: 2.10.1 Evaluación y selección de proveedores y contratistas | C35: 2 | D35: MES 7
A36: HACER | B36: 2.11.1 Evaluación del impacto de cambios internos y externos en el Sistema de Gestión de Seguridad y Salud en el Trabajo SG-SST | C36: 1 | D36: MES 7
A37: HACER | B37: 3.1.1 Descripcion sociodemografica.Diagnostico de Condiciones de Salud | C37: 1 | D37: MES 8 | E37: =SUM(C37:C41) -> 5 | F37: 5
A38: HACER | B38: 3.1.2 Actividades de Promoción y Prevención en Salud | C38: 1 | D38: MES 8
A39: HACER | B39: 3.1.3 Información al médico de los perfiles de cargo | C39: 1 | D39: MES 8
A40: HACER | B40: 3.1.4 Realización de los evaluaciones médicas ocupacionales: Peligros- Periodicidad Comunicación al Trabajador | C40: 1 | D40: MES 8
A41: HACER | B41: 3.1.5 Custodia de Historias Clínicas | C41: 1
A42: HACER | B42: 3.1.6 Restricciones y recomendaciones médico laborales | C42: 1 | D42: MES 9 | E42: =SUM(C42:C45) -> 4 | F42: 4
A43: HACER | B43: 3.1.7 Estilos de vida y entornos saludables (controles tabaquismo, alcoholismo, farmacodependencia y otros) | C43: 1 | D43: MES 9
A44: HACER | B44: 3.1.8 Agua potable, servicios sanitarios y disposición de basuras | C44: 1 | D44: MES 9
A45: HACER | B45: 3.1.9 Eliminación adecuada de residuos sólidos, líquidos o gaseosos | C45: 1 | D45: MES 9
A46: HACER | B46: 3.2.1 Reporte de los accidentes de trabajo y enfermedad laboral a la ARL, EPS y Dirección Territorial del Ministerio de Trabajo | C46: 2 | D46: MES 10 | E46: =SUM(C46:C49) -> 6 | F46: 4
A47: HACER | B47: 3.2.2 Investigación de Incidentes, Accidentes y Enfermedades Laborales | C47: 2 | D47: MES 10
A48: HACER | B48: 3.2.3 Registro y análisis estadístico de Accidentes y Enfermedades Laborales | C48: 1 | D48: MES 10
A49: HACER | B49: 3.3.1 Medición de la frecuencia de la accidentalidad | C49: 1 | D49: MES 10
A50: HACER | B50: 3.3.2 Medición de la severidad de la accientalidad | C50: 1 | D50: MES 11 | E50: =SUM(C50:C54) -> 5 | F50: 5
A51: HACER | B51: 3.3.3 Medición de la mortalidad por accidentes de trabajo | C51: 1 | D51: MES11
A52: HACER | B52: 3.3.4 Medición de la prevalencia de Enfermedad Laboral | C52: 1 | D52: MES 11
A53: HACER | B53: 3.3.5 Medición de la incidencia de Enfermedad Laboral | C53: 1 | D53: MES 11
A54: HACER | B54: 3.3.6 Medición del ausentismo por causa medica | C54: 1 | D54: MES 11
A55: HACER | B55: 4.1.1 Metodología para la identificación de peligros, evaluación y valoración de los riesgos | C55: 4 | D55: MES 12 | E55: =SUM(C55:C58) -> 15 | F55: 4
A56: HACER | B56: 4.1.2 Identificación de peligros con participación de todos los niveles de la empresa | C56: 4 | D56: MES 12
A57: HACER | B57: 4.1.3 Identificación de sustancias catalogadas como carcinogenas o con toxicidad aguda. | C57: 3 | D57: MES 12
A58: HACER | B58: 4.1.4 Realización mediciones ambientales, químicos, físicos y biológicos | C58: 4 | D58: MES 12
A59: HACER | B59: 4.2.1 Implementacion de medidas de prevención y control frente a peligros/riesgos identificados | C59: 2,5 | D59: MES 13 | E59: =C59+C60+C61+C62 -> 10 | F59: 4
A60: HACER | B60: 4.2.2 Verifiacacion de aplicación de medidas de prevencion y control por parte de los trabajadores | C60: 2,5 | D60: MES 13
A61: HACER | B61: 4.2.3 Elaboracion de procedimientos, instructivos, fichas, protocolos | C61: 2,5 | D61: MES 13
A62: HACER | B62: 4.2.4 Realizacion de Inspecciones a instalaciones, maquinaria o equipos con participacion del COPASST. | C62: 2,5 | D62: MES 13
A63: HACER | B63: 4.2.5 Mantenimiento periódico de instalaciones, equipos, máquinas, herramientas | C63: 2,5 | D63: MES 14 | E63: =C63+C64+C65+C66 -> 6 | F63: 4
A64: HACER | B64: 4.2.6 Entrega de Elementos de Protección Persona EPP, se verifica con contratistas y subcontratistas | C64: 2,5 | D64: MES 14
A65: HACER | B65: 5.1.1 Se cuenta con el Plan de Prevención, Preparación y respuesta ante emergencias | C65: 0.5 | D65: MES 14
A66: VERIFICAR | B66: 5.1.2 Brigada de prevención conformada, capacitada y dotada | C66: 0.5 | D66: MES 14
A67: VERIFICAR | B67: 6.1.1 Definicion de Indicadores del SG-SST de acuerdo condiciones de la empresa | C67: 1.25 | D67: MES 15 | E67: =SUM(C67:C74) -> 15
A68: VERIFICAR | B68: 6.1.2 Las empresa adelanta auditoría por lo menos una vez al año | C68: 1.25 | D68: MES 15
A69: VERIFICAR | B69: 6.1.3 Revisión anual de la alta dirección, resultados de la auditoría | C69: 1.25 | D69: MES 15
A70: ACTUAR | B70: 6.1.4 Planificacion auditorias con el COPASST | C70: 1.25 | D70: MES 15
A71: ACTUAR | B71: 7.1.1 Definicion de acciones preventivas y correctivas con base en resultados del SG-SST | C71: 2.5 | D71: MES 15
A72: ACTUAR | B72: 7.1.2 Acciones de mejora conforme a revision de la alta direccion | C72: 2.5 | D72: MES 15
A73: ACTUAR | B73: 7.1.3 Acciones de mejora con base en investigaciones de accidentes de trabajo y enfermedades laborales | C73: 2.5 | D73: MES 15
A74: ACTUAR | B74: 7.1.4 Elaboracion Plan de mejoramiento, implementacin de medidas y acciones correctivas solicitadas por autoridades y ARL | C74: 2.5 | D74: MES 15
D75: MES 15
E76: =SUM(E2:E75) -> 107

Sheet VERO EMPRESAS ACTIVAS
A1: FECHA INICIO DEL PROGRAMA | B1: NOMBRE DE LA EMPRESA | C1: NIT | D1: MES DE INICIO COBERTURA | E1: MESES A CORTE 30 DE MAYO | F1: ACTIVO/INACTIVO | G1: % RESOLUCIÓN 0312 de 2019 | H1: ACCIONES PLANEADAS | I1: % AVANCE | J1: ESTADO INICIAL | K1: FECHA CORTE DE INFORME | L1: VALOR PROGRAMA | M1: AVANCE EN PRODUCTIVIDAD | N1: VALOR A FACTURAR | O1: DÍAS EN EL PROGRAMA | P1: ACIONES EJECUTADAS
A2: 45717 | B2: CARNES MONTECARLO | C2: 43476587 | D2: MARZO | E2: 3 | F2: ACTIVO | G2: 51.08 | H2: 14 | I2: 5 | J2: =IF(G2<=60,"CRÍTICO",IF(G2<=85,"MODERADO","ACEPTABLE")) -> CRÍTICO | K2: 45807 | L2: =VLOOKUP(C2,'CRM ANALISTAS'!$M$2:$Q$206,5,0) -> 106666 | M2: =VLOOKUP(B2,GRÁFICAS!$A$4:$C$28,3,0) -> 5 | N2: =L2*E2 -> 319998 | O2: 90 | P2: =(H2*I2)/100 -> 0.7
A3: 45717 | B3: OLGA LÓPEZ | C3: 43862379 | D3: MARZO | E3: 3 | F3: ACTIVO | G3: 56.83 | H3: 14 | I3: 3.5 | J3: =IF(G3<=60,"CRÍTICO",IF(G3<=85,"MODERADO","ACEPTABLE")) -> CRÍTICO | K3: 45807 | L3: =VLOOKUP(C3,'CRM ANALISTAS'!$M$2:$Q$206,5,0) -> 106666 | M3: =VLOOKUP(B3,GRÁFICAS!$A$4:$C$28,3,0) -> 3.5 | N3: =L3*E3 -> 319998 | O3: 90 | P3: =(H3*I3)/100 -> 0.49
A4: 45717 | B4: TROPICAL1987 | C4: 1039681747 | D4: MARZO | E4: 3 | F4: ACTIVO | G4: 34.08 | H4: 14 | I4: 8 | J4: =IF(G4<=60,"CRÍTICO",IF(G4<=85,"MODERADO","ACEPTABLE")) -> CRÍTICO | K4: 45807 | L4: =VLOOKUP(C4,'CRM ANALISTAS'!$M$2:$Q$206,5,0) -> 106666 | M4: =VLOOKUP(B4,GRÁFICAS!$A$4:$C$28,3,0) -> 8 | N4: =L4*E4 -> 319998 | O4: 90 | P4: =(H4*I4)/100 -> 1.12
A5: 45724 | B5: SUMINISTRO Y TRANSPORTE DE MATERIAL RIOS Y FLOREZ SAS | C5: 901590411 | D5: MARZO | E5: 3 | F5: ACTIVO | G5: 0 | H5: 14 | I5: 6 | J5: =IF(G5<=60,"CRÍTICO",IF(G5<=85,"MODERADO","ACEPTABLE")) -> CRÍTICO | K5: 45807 | L5: =VLOOKUP(C5,'CRM ANALISTAS'!$M$2:$Q$206,5,0) -> 106666 | M5: =VLOOKUP(B5,GRÁFICAS!$A$4:$C$28,3,0) -> 6 | N5: =L5*E5 -> 319998 | O5: 83 | P5: =(H5*I5)/100 -> 0.84
A6: 45731 | B6: TECCONS S.A.S | C6: 900709843 | D6: MARZO | E6: 3 | F6: ACTIVO | G6: 48.58 | H6: 14 | I6: 13 | J6: =IF(G6<=60,"CRÍTICO",IF(G6<=85,"MODERADO","ACEPTABLE")) -> CRÍTICO | K6: 45807 | L6: =VLOOKUP(C6,'CRM ANALISTAS'!$M$2:$Q$206,5,0) -> 213000 | M6: =VLOOKUP(B6,GRÁFICAS!$A$4:$C$28,3,0) -> 13 | N6: =L6*E6 -> 639000 | O6: 76 | P6: =(H6*I6)/100 -> 1.82
A7: 45733 | B7: SAÚL GÓMEZ | C7: 15384344 | D7: MARZO | E7: 3 | F7: ACTIVO | G7: 85.58 | H7: 14 | I7: 13 | J7: =IF(G7<=60,"CRÍTICO",IF(G7<=85,"MODERADO","ACEPTABLE")) -> ACEPTABLE | K7: 45807 | L7: =VLOOKUP(C7,'CRM ANALISTAS'!$M$2:$Q$206,5,0) -> 106666 | M7: =VLOOKUP(B7,GRÁFICAS!$A$4:$C$28,3,0) -> 13 | N7: =L7*E7 -> 319998 | O7: 74 | P7: =(H7*I7)/100 -> 1.82
A8: 45735 | B8: MADERAS SAN RAFAEL | C8: 1013654370 | D8: MARZO | E8: 3 | F8: ACTIVO | G8: 0 | H8: 14 | I8: 15 | J8: =IF(G8<=60,"CRÍTICO",IF(G8<=85,"MODERADO","ACEPTABLE")) -> CRÍTICO | K8: 45807 | L8: =VLOOKUP(C8,'CRM ANALISTAS'!$M$2:$Q$206,5,0) -> 213000 | M8: =VLOOKUP(B8,GRÁFICAS!$A$4:$C$28,3,0) -> 15 | N8: =L8*E8 -> 639000 | O8: 72 | P8: =(H8*I8)/100 -> 2.1
A9: 45737 | B9: LOPETRANS SAS | C9: 901636833 | D9: MARZO | E9: 3 | F9: ACTIVO | G9: 50.58 | H9: 14 | I9: 23 | J9: =IF(G9<=60,"CRÍTICO",IF(G9<=85,"MODERADO","ACEPTABLE")) -> CRÍTICO | K9: 45807 | L9: =VLOOKUP(C9,'CRM ANALISTAS'!$M$2:$Q$206,5,0) -> 106666 | M9: =VLOOKUP(B9,GRÁFICAS!$A$4:$C$28,3,0) -> 23 | N9: =L9*E9 -> 319998 | O9: 70 | P9: =(H9*I9)/100 -> 3.22
A10: 45741 | B10: INVERSIONES VALLEJUELO S.A.S. | C10: 900655932 | D10: MARZO | E10: 3 | F10: ACTIVO | G10: 91.58 | H10: 14 | I10: 11 | J10: =IF(G10<=60,"CRÍTICO",IF(G10<=85,"MODERADO","ACEPTABLE")) -> ACEPTABLE | K10: 45807 | L10: =VLOOKUP(C10,'CRM ANALISTAS'!$M$2:$Q$206,5,0) -> 106666 | M10: =VLOOKUP(B10,GRÁFICAS!$A$4:$C$28,3,0) -> 11 | N10: =L10*E10 -> 319998 | O10: 66 | P10: =(H10*I10)/100 -> 1.54
A11: 45741 | B11: JULIAN GALLEGO CASTRO | C11: 15448886 | D11: MARZO | E11: 3 | F11: ACTIVO | G11: 6 | H11: 14 | I11: 15 | J11: =IF(G11<=60,"CRÍTICO",IF(G11<=85,"MODERADO","ACEPTABLE")) -> CRÍTICO | K11: 45807 | L11: =VLOOKUP(C11,'CRM ANALISTAS'!$M$2:$Q$206,5,0) -> 106666 | M11: =VLOOKUP(B11,GRÁFICAS!$A$4:$C$28,3,0) -> 15 | N11: =L11*E11 -> 319998 | O11: 66 | P11: =(H11*I11)/100 -> 2.1
A12: 45742 | B12: JOSE ARENAS ORTEGA | C12: 91292432 | D12: MARZO | E12: 1 | F12: INACTIVO | G12: 0 | H12: 0 | I12: 0 | J12: =IF(G12<=60,"CRÍTICO",IF(G12<=85,"MODERADO","ACEPTABLE")) -> CRÍTICO | K12: 45807 | L12: 0 | M12: 0 | N12: =L12*E12 -> 0 | O12: 0 | P12: =(H12*I12)/100 -> 0
A13: 45742 | B13: URANTUS GREENHOUSES S.A.S | C13: 901268585 | D13: MARZO | E13: 3 | F13: ACTIVO | G13: 91.58 | H13: 14 | I13: 18.5 | J13: =IF(G13<=60,"CRÍTICO",IF(G13<=85,"MODERADO","ACEPTABLE")) -> ACEPTABLE | K13: 45807 | L13: =VLOOKUP(C13,'CRM ANALISTAS'!$M$2:$Q$206,5,0) -> 213000 | M13: =VLOOKUP(B13,GRÁFICAS!$A$4:$C$28,3,0) -> 18.5 | N13: =L13*E13 -> 639000 | O13: 65 | P13: =(H13*I13)/100 -> 2.59
A14: 45744 | B14: ANA CAMPUZANO ARBOLEDA | C14: 1007445947 | D14: MARZO | E14: 3 | F14: ACTIVO | G14: 0 | H14: 14 | I14: 17.5 | J14: =IF(G14<=60,"CRÍTICO",IF(G14<=85,"MODERADO","ACEPTABLE")) -> CRÍTICO | K14: 45807 | L14: =VLOOKUP(C14,'CRM ANALISTAS'!$M$2:$Q$206,5,0) -> 106666 | M14: =VLOOKUP(B14,GRÁFICAS!$A$4:$C$28,3,0) -> 17.5 | N14: =L14*E14 -> 319998 | O14: 63 | P14: =(H14*I14)/100 -> 2.45
A15: 45744 | B15: LACTEOS BUENA VISTA SABORES NATURALES S A | C15: 900167311 | D15: MARZO | E15: 3 | F15: ACTIVO | G15: 0 | H15: 14 | I15: 18 | J15: =IF(G15<=60,"CRÍTICO",IF(G15<=85,"MODERADO","ACEPTABLE")) -> CRÍTICO | K15: 45807 | L15: =VLOOKUP(C15,'CRM ANALISTAS'!$M$2:$Q$206,5,0) -> 106666 | M15: =VLOOKUP(B15,GRÁFICAS!$A$4:$C$28,3,0) -> 18 | N15: =L15*E15 -> 319998 | O15: 63 | P15: =(H15*I15)/100 -> 2.52
A16: 45751 | B16: ALMA BOTANICA SAS | C16: 901817841 | D16: ABRIL | E16: 2 | F16: ACTIVO | G16: 0 | H16: 10 | I16: 10 | J16: =IF(G16<=60,"CRÍTICO",IF(G16<=85,"MODERADO","ACEPTABLE")) -> CRÍTICO | K16: 45807 | L16: =VLOOKUP(C16,'CRM ANALISTAS'!$M$2:$Q$206,5,0) -> 213000 | M16: =VLOOKUP(B16,GRÁFICAS!$A$4:$C$28,3,0) -> 10 | N16: =L16*E16 -> 426000 | O16: 56
A17: 45751 | B17: BLACKRIVER FLOWERS SAS C I | C17: 900841005 | D17: ABRIL | E17: 2 | F17: ACTIVO | G17: 99.08 | H17: 10 | I17: 14.5 | J17: =IF(G17<=60,"CRÍTICO",IF(G17<=85,"MODERADO","ACEPTABLE")) -> ACEPTABLE | K17: 45807 | L17: =VLOOKUP(C17,'CRM ANALISTAS'!$M$2:$Q$206,5,0) -> 106666 | M17: =VLOOKUP(B17,GRÁFICAS!$A$4:$C$28,3,0) -> 14.5 | N17: =L17*E17 -> 213332 | O17: 56
A18: 45751 | B18: BORJA FLOWERS SAS | C18: 901546567 | D18: ABRIL | E18: 2 | F18: ACTIVO | G18: 0 | H18: 10 | I18: 5 | J18: =IF(G18<=60,"CRÍTICO",IF(G18<=85,"MODERADO","ACEPTABLE")) -> CRÍTICO | K18: 45807 | L18: =VLOOKUP(C18,'CRM ANALISTAS'!$M$2:$Q$206,5,0) -> 106666 | M18: =VLOOKUP(B18,GRÁFICAS!$A$4:$C$28,3,0) -> 5 | N18: =L18*E18 -> 213332 | O18: 56
A19: 45751 | B19: CI FLORES MUNDO COLORES SAS | C19: 900509996 | D19: ABRIL | E19: 2 | F19: ACTIVO | G19: 53.3 | H19: 10 | I19: 17.5 | J19: =IF(G19<=60,"CRÍTICO",IF(G19<=85,"MODERADO","ACEPTABLE")) -> CRÍTICO | K19: 45807 | L19: =VLOOKUP(C19,'CRM ANALISTAS'!$M$2:$Q$206,5,0) -> 106666 | M19: =VLOOKUP(B19,GRÁFICAS!$A$4:$C$28,3,0) -> 17.5 | N19: =L19*E19 -> 213332 | O19: 56
A20: 45751 | B20: EMTURPE LIMITADA | C20: 900112921 | D20: ABRIL | E20: 2 | F20: ACTIVO | G20: 0 | H20: 10 | I20: 11 | J20: =IF(G20<=60,"CRÍTICO",IF(G20<=85,"MODERADO","ACEPTABLE")) -> CRÍTICO | K20: 45807 | L20: =VLOOKUP(C20,'CRM ANALISTAS'!$M$2:$Q$206,5,0) -> 213000 | M20: =VLOOKUP(B20,GRÁFICAS!$A$4:$C$28,3,0) -> 11 | N20: =L20*E20 -> 426000 | O20: 56
A21: 45751 | B21: PROSOLAR S.A.S | C21: 901039724 | D21: ABRIL | E21: 2 | F21: ACTIVO | G21: 0 | H21: 10 | I21: 8.5 | J21: =IF(G21<=60,"CRÍTICO",IF(G21<=85,"MODERADO","ACEPTABLE")) -> CRÍTICO | K21: 45807 | L21: =VLOOKUP(C21,'CRM ANALISTAS'!$M$2:$Q$206,5,0) -> 106666 | M21: =VLOOKUP(B21,GRÁFICAS!$A$4:$C$28,3,0) -> 8.5 | N21: =L21*E21 -> 213332 | O21: 56
A22: 45751 | B22: VANESSA VARGAS ALZATE | C22: 1037649854 | D22: ABRIL | E22: 2 | F22: ACTIVO | G22: 57.58 | H22: 10 | I22: 14 | J22: =IF(G22<=60,"CRÍTICO",IF(G22<=85,"MODERADO","ACEPTABLE")) -> CRÍTICO | K22: 45807 | L22: =VLOOKUP(C22,'CRM ANALISTAS'!$M$2:$Q$206,5,0) -> 106666 | M22: =VLOOKUP(B22,GRÁFICAS!$A$4:$C$28,3,0) -> 14 | N22: =L22*E22 -> 213332 | O22: 56
A23: 45775 | B23: HYDRANFLOWERS S.A.S | C23: 901166099 | D23: ABRIL | E23: 2 | F23: ACTIVO | G23: 0 | H23: 10 | I23: 5.5 | J23: =IF(G23<=60,"CRÍTICO",IF(G23<=85,"MODERADO","ACEPTABLE")) -> CRÍTICO | K23: 45807 | L23: =VLOOKUP(C23,'CRM ANALISTAS'!$M$2:$Q$206,5,0) -> 106666 | M23: =VLOOKUP(B23,GRÁFICAS!$A$4:$C$28,3,0) -> 5.5 | N23: =L23*E23 -> 213332 | O23: 32
A24: 45797 | B24: AGROINSUMOS VILLACLARA SAS | C24: 901250630 | D24: MAYO | E24: 1 | F24: ACTIVO | G24: 77.31 | H24: 5 | I24: 2 | J24: =IF(G24<=60,"CRÍTICO",IF(G24<=85,"MODERADO","ACEPTABLE")) -> MODERADO | K24: 45807 | L24: =VLOOKUP(C24,'CRM ANALISTAS'!$M$2:$Q$206,5,0) -> 106666 | M24: =VLOOKUP(B24,GRÁFICAS!$A$4:$C$28,3,0) -> 2 | N24: =L24*E24 -> 106666 | O24: 10
A25: 45797 | B25: ESTRUCTURAS METALICAS DEL CHOCO | C25: 900530803 | D25: MAYO | E25: 1 | F25: ACTIVO | G25: 6 | H25: 5 | I25: 1 | J25: =IF(G25<=60,"CRÍTICO",IF(G25<=85,"MODERADO","ACEPTABLE")) -> CRÍTICO | K25: 45807 | L25: =VLOOKUP(C25,'CRM ANALISTAS'!$M$2:$Q$206,5,0) -> 106666 | M25: =VLOOKUP(B25,GRÁFICAS!$A$4:$C$28,3,0) -> 1 | N25: =L25*E25 -> 106666 | O25: 10
A26: 45797 | B26: FOTO SCANNER | C26: 1128395305 | D26: MAYO | E26: 1 | F26: ACTIVO | G26: 0 | H26: 5 | I26: 4 | J26: =IF(G26<=60,"CRÍTICO",IF(G26<=85,"MODERADO","ACEPTABLE")) -> CRÍTICO | K26: 45807 | L26: =VLOOKUP(C26,'CRM ANALISTAS'!$M$2:$Q$206,5,0) -> 106666 | M26: =VLOOKUP(B26,GRÁFICAS!$A$4:$C$28,3,0) -> 4 | N26: =L26*E26 -> 106666 | O26: 10
N27: =SUM(N2:N27) -> 7568970
A32: Empresa Nueva | C32: 15384344
C33: 1013654370
A34: Maria Clara Vélez Viana | C34: 901166099
A35: CC 1017241965 | C35: 901636833
A36: FECHA DE NACIMIENTO: 27/11/1996 | C36: 15448886
A37: maclaravelez@gmail.com | C37: 900655932
A38: +57 311 4046195 | C38: 901268585
A39: Estación Vive San José | C39: 900167311
A40: 23 EMPLEADOS | C40: 900709843
C41: 1007445947
C42: 900509996
C43: 900841005
C44: 901546567
C45: 900112921
C46: 1037649854
C47: 901039724
C48: 901817841
C49: 901590411
C50: 43862379
C51: 1039681747
C52: 43476587

Sheet LISTA DESPLEGABLE
A1: Atención de empresas
A2: Ciclo PHVA
A3: PLANEAR
A4: HACER
A5: VERIFICAR
A6: ACTUAR
A11: Programas
A12: Tu Empresa Segura
A13: Salud 360
A14: Crecer Juntos
A16: SI
A17: NO CONEXIÓN
... A22: SAVANNA
